Workbook

Sheet Обзор F1
A1: CAPEXLY · рабочий комплект | E1: 14.10.2026 · редакция F1
A2: Не факт продаж. Все расчёты — сценарные гипотезы.
A3: Начните с допущений. Синие клетки — ввод; формулы — расчёт.
A5: Показатель | B5: Слабый F1 | C5: Рабочий F1 | D5: Сильный F1 | E5: Как читать
A6: Клиенты на конец м12 | B6: ='Слабый F1'!H13 -> 12.940494 | C6: ='Рабочий F1'!H13 -> 48.317569 | D6: ='Сильный F1'!H13 -> 101.09655 | E6: Ожидаемое значение, не округлённая история
A7: MRR на конец м12, руб. | B7: ='Слабый F1'!K13 -> 128110.89 | C7: ='Рабочий F1'!K13 -> 719931.78 | D7: ='Сильный F1'!K13 -> 2011821.3 | E7: Повторяемая подписка; разовые платежи исключены
A8: Начислено за 12 мес., руб. | B8: =SUM('Слабый F1'!N2:N13) -> 601873.96 | C8: =SUM('Рабочий F1'!N2:N13) -> 3314796.4 | D8: =SUM('Сильный F1'!N2:N13) -> 9167201.1 | E8: Смешение подписки и отдельных пилотов/документов
A9: Касса на конец м12, руб. | B9: ='Слабый F1'!X13 -> -367545.88 | C9: ='Рабочий F1'!X13 -> 836917.64 | D9: ='Сильный F1'!X13 -> 4564952.2 | E9: С учётом задержки поступлений
A10: Минимальная касса, руб. | B10: =MIN('Слабый F1'!X2:X13) -> -367545.88 | C10: =MIN('Рабочий F1'!X2:X13) -> 50785.367 | D10: =MIN('Сильный F1'!X2:X13) -> 100762.6 | E10: Проверяется весь помесячный путь
A11: Доп. деньги до нулевой кассы | B11: =MAX(0,-MIN('Слабый F1'!X2:X13)) -> 367545.88 | C11: =MAX(0,-MIN('Рабочий F1'!X2:X13)) -> 0 | D11: =MAX(0,-MIN('Сильный F1'!X2:X13)) -> 0 | E11: Без резервной подушки; не обещание финансирования
A12: Экономический результат м12 | B12: ='Слабый F1'!T13 -> -97650.141 | C12: ='Рабочий F1'!T13 -> 175049.96 | D12: ='Сильный F1'!T13 -> 937381.97 | E12: Включает неоплаченный труд основателя
A13: Минимальное финансирование с резервом | B13: =MAX(0,'Допущения F1'!B20*MAX('Слабый F1'!Q2:Q13)-MIN('Слабый F1'!X2:X13)) -> 547545.88 | C13: =MAX(0,'Допущения F1'!C20*MAX('Рабочий F1'!Q2:Q13)-MIN('Рабочий F1'!X2:X13)) -> 129214.63 | D13: =MAX(0,'Допущения F1'!D20*MAX('Сильный F1'!Q2:Q13)-MIN('Сильный F1'!X2:X13)) -> 79237.396 | E13: Добавка для покрытия фиксированных выплат × резерв
A15: ЧТО СОХРАНЕНО
A16: 57 исходных ID | B16: 41 клиентская запись | C16: 11 платформенных | D16: 5 GTM | E16: Не 57 независимых продуктов
A17: 125 сигналов | B17: Пересказ из Iter6 | E17: Исходный внешний пакет отсутствует
A18: Реестр доказательств | B18: Тезисы F1 / Источники Sources | E18: URL и доменные упоминания различены
A19: Касса и экономика | B19: Неоплаченный труд виден | E19: Доставка/подпись оплачиваются клиентом напрямую

Sheet Допущения F1
A1: Драйвер | B1: Слабый F1 | C1: Рабочий F1 | D1: Сильный F1 | E1: Основание / ограничения
A2: Начальная касса, руб. | B2: 150000 | C2: 150000 | D2: 150000 | E2: Займ учредителя из архива; не подтверждён выпиской
A3: Стартовые затраты, руб. | B3: 31000 | C3: 31000 | D3: 31000 | E3: Стартовый бюджет v2, не коммерческая смета
A4: Ответы / квалифицированные контакты | B4: 0.15 | C4: 0.25 | D4: 0.35 | E4: Новая тестовая гипотеза; не конверсия массовых писем
A5: Демо / ответы | B5: 0.4 | C5: 0.5 | D5: 0.6 | E5: Новая тестовая гипотеза
A6: Оплаты / демо | B6: 0.15 | C6: 0.25 | D6: 0.3 | E6: Новая тестовая гипотеза
A7: Отток клиентов за месяц | B7: 0.06 | C7: 0.04 | D7: 0.03 | E7: Гипотеза; измерять когортами
A8: ARPU подписки, руб./мес. | B8: 9900 | C8: 14900 | D8: 19900 | E8: Новая тестовая гипотеза; не готовый тариф
A9: Документов на активного клиента/мес. | B9: 10 | C9: 10 | D9: 10 | E9: Гипотеза использования
A10: Стоимость AI/OCR на документ, руб. | B10: 50 | C10: 50 | D10: 50 | E10: Бюджетная гипотеза; измерять все попытки и OCR
A11: Проверка одного документа, часов | B11: 0.35 | C11: 0.35 | D11: 0.35 | E11: Бюджетная гипотеза эксперта
A12: Ставка эксперта, руб./час | B12: 2000 | C12: 2000 | D12: 2000 | E12: Бюджетная гипотеза; заменяется договором
A13: Доля выручки, поступающая в следующем месяце | B13: 0.5 | C13: 0.3 | D13: 0.1 | E13: Упрощённая задержка оплаты на один месяц
... A20: Резерв в месяцах постоянных платежей | B20: 3 | C20: 3 | D20: 3 | E20: Управленческое правило, не норматив

Sheet План месяцев F1
A1: Месяц | B1: Период | C1: Контакты с основанием | D1: Партнёрские новые клиенты | E1: Пилоты, отдельных шт. | F1: Разовые документы, шт. | G1: Доля документов с экспертной проверкой | H1: Постоянные платежи, руб. | I1: Подтверждённое финансирование, руб. | J1: Комментарий
A2: 1 | B2: ноя 2026 | C2: 40 | D2: 0 | E2: 0 | F2: 0 | G2: 1 | H2: 30000 | I2: 0 | J2: Прогноз; вводить факт. Финансирование F1 только при подтверждении.
A3: 2 | B3: дек 2026 | C3: 60 | D3: 0 | E3: 0 | F3: 0 | G3: 1 | H3: 30000 | I3: 0 | J3: Прогноз; вводить факт. Финансирование F1 только при подтверждении.
A4: 3 | B4: янв 2027 | C4: 80 | D4: 0 | E4: 0 | F4: 0 | G4: 1 | H4: 30000 | I4: 0 | J4: Прогноз; вводить факт. Финансирование F1 только при подтверждении.
A5: 4 | B5: фев 2027 | C5: 100 | D5: 0 | E5: 0 | F5: 0 | G5: 1 | H5: 40000 | I5: 0 | J5: Прогноз; вводить факт. Финансирование F1 только при подтверждении.
A6: 5 | B6: мар 2027 | C6: 120 | D6: 0 | E6: 0 | F6: 0 | G6: 1 | H6: 40000 | I6: 0 | J6: Прогноз; вводить факт. Финансирование F1 только при подтверждении.
A7: 6 | B7: апр 2027 | C7: 140 | D7: 0 | E7: 0 | F7: 0 | G7: 1 | H7: 40000 | I7: 0 | J7: Прогноз; вводить факт. Финансирование F1 только при подтверждении.
A8: 7 | B8: май 2027 | C8: 160 | D8: 0 | E8: 0 | F8: 0 | G8: 1 | H8: 50000 | I8: 0 | J8: Прогноз; вводить факт. Финансирование F1 только при подтверждении.
A9: 8 | B9: июн 2027 | C9: 180 | D9: 0 | E9: 0 | F9: 0 | G9: 1 | H9: 50000 | I9: 0 | J9: Прогноз; вводить факт. Финансирование F1 только при подтверждении.
A10: 9 | B10: июл 2027 | C10: 200 | D10: 0 | E10: 0 | F10: 0 | G10: 1 | H10: 50000 | I10: 0 | J10: Прогноз; вводить факт. Финансирование F1 только при подтверждении.
A11: 10 | B11: авг 2027 | C11: 220 | D11: 0 | E11: 0 | F11: 0 | G11: 1 | H11: 60000 | I11: 0 | J11: Прогноз; вводить факт. Финансирование F1 только при подтверждении.
A12: 11 | B12: сен 2027 | C12: 240 | D12: 0 | E12: 0 | F12: 0 | G12: 1 | H12: 60000 | I12: 0 | J12: Прогноз; вводить факт. Финансирование F1 только при подтверждении.
A13: 12 | B13: окт 2027 | C13: 260 | D13: 0 | E13: 0 | F13: 0 | G13: 1 | H13: 60000 | I13: 0 | J13: Прогноз; вводить факт. Финансирование F1 только при подтверждении.

Sheet Слабый F1
A1: Мес. | B1: Контакты | C1: Ответы | D1: Демо | E1: Новые прямые | F1: Новые партн. | G1: Отток, клиентов | H1: Клиенты на конец | I1: Средние активные | J1: ARPU, руб. | K1: MRR конец, руб. | L1: Разовые пилоты | M1: Разовые документы | N1: Начислено всего | O1: Прямые затраты | P1: Вклад до фикс. | Q1: Фикс. выплаты | R1: Налоговый резерв | S1: Неопл. труд основ. | T1: Экон. результат | U1: Денежные поступления | V1: Денежные расходы | W1: Подтвержд. деньги | X1: Касса на конец | Y1: Запас кассы
A2: ='План месяцев F1'!A2 -> 1 | B2: ='План месяцев F1'!C2 -> 40 | C2: =B2*'Допущения F1'!$B$4 -> 6 | D2: =C2*'Допущения F1'!$B$5 -> 2.4 | E2: =D2*'Допущения F1'!$B$6 -> 0.36 | F2: ='План месяцев F1'!D2 -> 0 | G2: =0*'Допущения F1'!$B$7 -> 0 | H2: =0-G2+E2+F2 -> 0.36 | I2: =(0+H2)/2 -> 0.18 | J2: ='Допущения F1'!$B$8 -> 9900 | K2: =H2*J2 -> 3564 | L2: ='План месяцев F1'!E2*'Допущения F1'!$B$17 -> 0 | M2: ='План месяцев F1'!F2*'Допущения F1'!$B$16 -> 0 | N2: =I2*J2+L2+M2 -> 1782 | O2: =(I2*'Допущения F1'!$B$9+'План месяцев F1'!F2)*('Допущения F1'!$B$10+'План месяцев F1'!G2*'Допущения F1'!$B$11*'Допущения F1'!$B$12)+F2*J2*'Допущения F1'!$B$15+L2*'План месяцев F1'!G2 -> 1350 | P2: =N2-O2 -> 432 | Q2: ='План месяцев F1'!H2+'Допущения F1'!$B$18 -> 30000 | R2: =U2*'Допущения F1'!$B$14 -> 53.46 | S2: =MAX(0,'Допущения F1'!$B$19-'Допущения F1'!$B$18) -> 60000 | T2: =P2-Q2-R2-S2 -> -89621.46 | U2: =N2*(1-'Допущения F1'!$B$13)+(0)*'Допущения F1'!$B$13 -> 891 | V2: =O2+Q2+R2 -> 31403.46 | W2: ='План месяцев F1'!I2 -> 0 | X2: ='Допущения F1'!$B$2-'Допущения F1'!$B$3+U2-V2+W2 -> 88487.54 | Y2: =IF(X2<Q2*'Допущения F1'!$B$20,"НИЖЕ РЕЗЕРВА","РЕЗЕРВ ЕСТЬ") -> НИЖЕ РЕЗЕРВА
A3: ='План месяцев F1'!A3 -> 2 | B3: ='План месяцев F1'!C3 -> 60 | C3: =B3*'Допущения F1'!$B$4 -> 9 | D3: =C3*'Допущения F1'!$B$5 -> 3.6 | E3: =D3*'Допущения F1'!$B$6 -> 0.54 | F3: ='План месяцев F1'!D3 -> 0 | G3: =H2*'Допущения F1'!$B$7 -> 0.0216 | H3: =H2-G3+E3+F3 -> 0.8784 | I3: =(H2+H3)/2 -> 0.6192 | J3: ='Допущения F1'!$B$8 -> 9900 | K3: =H3*J3 -> 8696.16 | L3: ='План месяцев F1'!E3*'Допущения F1'!$B$17 -> 0 | M3: ='План месяцев F1'!F3*'Допущения F1'!$B$16 -> 0 | N3: =I3*J3+L3+M3 -> 6130.08 | O3: =(I3*'Допущения F1'!$B$9+'План месяцев F1'!F3)*('Допущения F1'!$B$10+'План месяцев F1'!G3*'Допущения F1'!$B$11*'Допущения F1'!$B$12)+F3*J3*'Допущения F1'!$B$15+L3*'План месяцев F1'!G3 -> 4644 | P3: =N3-O3 -> 1486.08 | Q3: ='План месяцев F1'!H3+'Допущения F1'!$B$18 -> 30000 | R3: =U3*'Допущения F1'!$B$14 -> 237.3624 | S3: =MAX(0,'Допущения F1'!$B$19-'Допущения F1'!$B$18) -> 60000 | T3: =P3-Q3-R3-S3 -> -88751.282 | U3: =N3*(1-'Допущения F1'!$B$13)+(N2)*'Допущения F1'!$B$13 -> 3956.04 | V3: =O3+Q3+R3 -> 34881.362 | W3: ='План месяцев F1'!I3 -> 0 | X3: =X2+U3-V3+W3 -> 57562.218 | Y3: =IF(X3<Q3*'Допущения F1'!$B$20,"НИЖЕ РЕЗЕРВА","РЕЗЕРВ ЕСТЬ") -> НИЖЕ РЕЗЕРВА
A4: ='План месяцев F1'!A4 -> 3 | B4: ='План месяцев F1'!C4 -> 80 | C4: =B4*'Допущения F1'!$B$4 -> 12 | D4: =C4*'Допущения F1'!$B$5 -> 4.8 | E4: =D4*'Допущения F1'!$B$6 -> 0.72 | F4: ='План месяцев F1'!D4 -> 0 | G4: =H3*'Допущения F1'!$B$7 -> 0.052704 | H4: =H3-G4+E4+F4 -> 1.545696 | I4: =(H3+H4)/2 -> 1.212048 | J4: ='Допущения F1'!$B$8 -> 9900 | K4: =H4*J4 -> 15302.39 | L4: ='План месяцев F1'!E4*'Допущения F1'!$B$17 -> 0 | M4: ='План месяцев F1'!F4*'Допущения F1'!$B$16 -> 0 | N4: =I4*J4+L4+M4 -> 11999.275 | O4: =(I4*'Допущения F1'!$B$9+'План месяцев F1'!F4)*('Допущения F1'!$B$10+'План месяцев F1'!G4*'Допущения F1'!$B$11*'Допущения F1'!$B$12)+F4*J4*'Допущения F1'!$B$15+L4*'План месяцев F1'!G4 -> 9090.36 | P4: =N4-O4 -> 2908.9152 | Q4: ='План месяцев F1'!H4+'Допущения F1'!$B$18 -> 30000 | R4: =U4*'Допущения F1'!$B$14 -> 543.88066 | S4: =MAX(0,'Допущения F1'!$B$19-'Допущения F1'!$B$18) -> 60000 | T4: =P4-Q4-R4-S4 -> -87634.965 | U4: =N4*(1-'Допущения F1'!$B$13)+(N3)*'Допущения F1'!$B$13 -> 9064.6776 | V4: =O4+Q4+R4 -> 39634.241 | W4: ='План месяцев F1'!I4 -> 0 | X4: =X3+U4-V4+W4 -> 26992.655 | Y4: =IF(X4<Q4*'Допущения F1'!$B$20,"НИЖЕ РЕЗЕРВА","РЕЗЕРВ ЕСТЬ") -> НИЖЕ РЕЗЕРВА
A5: ='План месяцев F1'!A5 -> 4 | B5: ='План месяцев F1'!C5 -> 100 | C5: =B5*'Допущения F1'!$B$4 -> 15 | D5: =C5*'Допущения F1'!$B$5 -> 6 | E5: =D5*'Допущения F1'!$B$6 -> 0.9 | F5: ='План месяцев F1'!D5 -> 0 | G5: =H4*'Допущения F1'!$B$7 -> 0.09274176 | H5: =H4-G5+E5+F5 -> 2.3529542 | I5: =(H4+H5)/2 -> 1.9493251 | J5: ='Допущения F1'!$B$8 -> 9900 | K5: =H5*J5 -> 23294.247 | L5: ='План месяцев F1'!E5*'Допущения F1'!$B$17 -> 0 | M5: ='План месяцев F1'!F5*'Допущения F1'!$B$16 -> 0 | N5: =I5*J5+L5+M5 -> 19298.319 | O5: =(I5*'Допущения F1'!$B$9+'План месяцев F1'!F5)*('Допущения F1'!$B$10+'План месяцев F1'!G5*'Допущения F1'!$B$11*'Допущения F1'!$B$12)+F5*J5*'Допущения F1'!$B$15+L5*'План месяцев F1'!G5 -> 14619.938 | P5: =N5-O5 -> 4678.3803 | Q5: ='План месяцев F1'!H5+'Допущения F1'!$B$18 -> 40000 | R5: =U5*'Допущения F1'!$B$14 -> 938.92782 | S5: =MAX(0,'Допущения F1'!$B$19-'Допущения F1'!$B$18) -> 60000 | T5: =P5-Q5-R5-S5 -> -96260.548 | U5: =N5*(1-'Допущения F1'!$B$13)+(N4)*'Допущения F1'!$B$13 -> 15648.797 | V5: =O5+Q5+R5 -> 55558.866 | W5: ='План месяцев F1'!I5 -> 0 | X5: =X4+U5-V5+W5 -> -12917.415 | Y5: =IF(X5<Q5*'Допущения F1'!$B$20,"НИЖЕ РЕЗЕРВА","РЕЗЕРВ ЕСТЬ") -> НИЖЕ РЕЗЕРВА
A6: ='План месяцев F1'!A6 -> 5 | B6: ='План месяцев F1'!C6 -> 120 | C6: =B6*'Допущения F1'!$B$4 -> 18 | D6: =C6*'Допущения F1'!$B$5 -> 7.2 | E6: =D6*'Допущения F1'!$B$6 -> 1.08 | F6: ='План месяцев F1'!D6 -> 0 | G6: =H5*'Допущения F1'!$B$7 -> 0.14117725 | H6: =H5-G6+E6+F6 -> 3.291777 | I6: =(H5+H6)/2 -> 2.8223656 | J6: ='Допущения F1'!$B$8 -> 9900 | K6: =H6*J6 -> 32588.592 | L6: ='План месяцев F1'!E6*'Допущения F1'!$B$17 -> 0 | M6: ='План месяцев F1'!F6*'Допущения F1'!$B$16 -> 0 | N6: =I6*J6+L6+M6 -> 27941.42 | O6: =(I6*'Допущения F1'!$B$9+'План месяцев F1'!F6)*('Допущения F1'!$B$10+'План месяцев F1'!G6*'Допущения F1'!$B$11*'Допущения F1'!$B$12)+F6*J6*'Допущения F1'!$B$15+L6*'План месяцев F1'!G6 -> 21167.742 | P6: =N6-O6 -> 6773.6775 | Q6: ='План месяцев F1'!H6+'Допущения F1'!$B$18 -> 40000 | R6: =U6*'Допущения F1'!$B$14 -> 1417.1921 | S6: =MAX(0,'Допущения F1'!$B$19-'Допущения F1'!$B$18) -> 60000 | T6: =P6-Q6-R6-S6 -> -94643.515 | U6: =N6*(1-'Допущения F1'!$B$13)+(N5)*'Допущения F1'!$B$13 -> 23619.869 | V6: =O6+Q6+R6 -> 62584.934 | W6: ='План месяцев F1'!I6 -> 0 | X6: =X5+U6-V6+W6 -> -51882.48 | Y6: =IF(X6<Q6*'Допущения F1'!$B$20,"НИЖЕ РЕЗЕРВА","РЕЗЕРВ ЕСТЬ") -> НИЖЕ РЕЗЕРВА
A7: ='План месяцев F1'!A7 -> 6 | B7: ='План месяцев F1'!C7 -> 140 | C7: =B7*'Допущения F1'!$B$4 -> 21 | D7: =C7*'Допущения F1'!$B$5 -> 8.4 | E7: =D7*'Допущения F1'!$B$6 -> 1.26 | F7: ='План месяцев F1'!D7 -> 0 | G7: =H6*'Допущения F1'!$B$7 -> 0.19750662 | H7: =H6-G7+E7+F7 -> 4.3542704 | I7: =(H6+H7)/2 -> 3.8230237 | J7: ='Допущения F1'!$B$8 -> 9900 | K7: =H7*J7 -> 43107.277 | L7: ='План месяцев F1'!E7*'Допущения F1'!$B$17 -> 0 | M7: ='План месяцев F1'!F7*'Допущения F1'!$B$16 -> 0 | N7: =I7*J7+L7+M7 -> 37847.934 | O7: =(I7*'Допущения F1'!$B$9+'План месяцев F1'!F7)*('Допущения F1'!$B$10+'План месяцев F1'!G7*'Допущения F1'!$B$11*'Допущения F1'!$B$12)+F7*J7*'Допущения F1'!$B$15+L7*'План месяцев F1'!G7 -> 28672.678 | P7: =N7-O7 -> 9175.2568 | Q7: ='План месяцев F1'!H7+'Допущения F1'!$B$18 -> 40000 | R7: =U7*'Допущения F1'!$B$14 -> 1973.6806 | S7: =MAX(0,'Допущения F1'!$B$19-'Допущения F1'!$B$18) -> 60000 | T7: =P7-Q7-R7-S7 -> -92798.424 | U7: =N7*(1-'Допущения F1'!$B$13)+(N6)*'Допущения F1'!$B$13 -> 32894.677 | V7: =O7+Q7+R7 -> 70646.358 | W7: ='План месяцев F1'!I7 -> 0 | X7: =X6+U7-V7+W7 -> -89634.161 | Y7: =IF(X7<Q7*'Допущения F1'!$B$20,"НИЖЕ РЕЗЕРВА","РЕЗЕРВ ЕСТЬ") -> НИЖЕ РЕЗЕРВА
A8: ='План месяцев F1'!A8 -> 7 | B8: ='План месяцев F1'!C8 -> 160 | C8: =B8*'Допущения F1'!$B$4 -> 24 | D8: =C8*'Допущения F1'!$B$5 -> 9.6 | E8: =D8*'Допущения F1'!$B$6 -> 1.44 | F8: ='План месяцев F1'!D8 -> 0 | G8: =H7*'Допущения F1'!$B$7 -> 0.26125622 | H8: =H7-G8+E8+F8 -> 5.5330141 | I8: =(H7+H8)/2 -> 4.9436423 | J8: ='Допущения F1'!$B$8 -> 9900 | K8: =H8*J8 -> 54776.84 | L8: ='План месяцев F1'!E8*'Допущения F1'!$B$17 -> 0 | M8: ='План месяцев F1'!F8*'Допущения F1'!$B$16 -> 0 | N8: =I8*J8+L8+M8 -> 48942.058 | O8: =(I8*'Допущения F1'!$B$9+'План месяцев F1'!F8)*('Допущения F1'!$B$10+'План месяцев F1'!G8*'Допущения F1'!$B$11*'Допущения F1'!$B$12)+F8*J8*'Допущения F1'!$B$15+L8*'План месяцев F1'!G8 -> 37077.317 | P8: =N8-O8 -> 11864.741 | Q8: ='План месяцев F1'!H8+'Допущения F1'!$B$18 -> 50000 | R8: =U8*'Допущения F1'!$B$14 -> 2603.6998 | S8: =MAX(0,'Допущения F1'!$B$19-'Допущения F1'!$B$18) -> 60000 | T8: =P8-Q8-R8-S8 -> -100738.96 | U8: =N8*(1-'Допущения F1'!$B$13)+(N7)*'Допущения F1'!$B$13 -> 43394.996 | V8: =O8+Q8+R8 -> 89681.017 | W8: ='План месяцев F1'!I8 -> 0 | X8: =X7+U8-V8+W8 -> -135920.18 | Y8: =IF(X8<Q8*'Допущения F1'!$B$20,"НИЖЕ РЕЗЕРВА","РЕЗЕРВ ЕСТЬ") -> НИЖЕ РЕЗЕРВА
A9: ='План месяцев F1'!A9 -> 8 | B9: ='План месяцев F1'!C9 -> 180 | C9: =B9*'Допущения F1'!$B$4 -> 27 | D9: =C9*'Допущения F1'!$B$5 -> 10.8 | E9: =D9*'Допущения F1'!$B$6 -> 1.62 | F9: ='План месяцев F1'!D9 -> 0 | G9: =H8*'Допущения F1'!$B$7 -> 0.33198085 | H9: =H8-G9+E9+F9 -> 6.8210333 | I9: =(H8+H9)/2 -> 6.1770237 | J9: ='Допущения F1'!$B$8 -> 9900 | K9: =H9*J9 -> 67528.23 | L9: ='План месяцев F1'!E9*'Допущения F1'!$B$17 -> 0 | M9: ='План месяцев F1'!F9*'Допущения F1'!$B$16 -> 0 | N9: =I9*J9+L9+M9 -> 61152.535 | O9: =(I9*'Допущения F1'!$B$9+'План месяцев F1'!F9)*('Допущения F1'!$B$10+'План месяцев F1'!G9*'Допущения F1'!$B$11*'Допущения F1'!$B$12)+F9*J9*'Допущения F1'!$B$15+L9*'План месяцев F1'!G9 -> 46327.678 | P9: =N9-O9 -> 14824.857 | Q9: ='План месяцев F1'!H9+'Допущения F1'!$B$18 -> 50000 | R9: =U9*'Допущения F1'!$B$14 -> 3302.8378 | S9: =MAX(0,'Допущения F1'!$B$19-'Допущения F1'!$B$18) -> 60000 | T9: =P9-Q9-R9-S9 -> -98477.981 | U9: =N9*(1-'Допущения F1'!$B$13)+(N8)*'Допущения F1'!$B$13 -> 55047.297 | V9: =O9+Q9+R9 -> 99630.516 | W9: ='План месяцев F1'!I9 -> 0 | X9: =X8+U9-V9+W9 -> -180503.4 | Y9: =IF(X9<Q9*'Допущения F1'!$B$20,"НИЖЕ РЕЗЕРВА","РЕЗЕРВ ЕСТЬ") -> НИЖЕ РЕЗЕРВА
A10: ='План месяцев F1'!A10 -> 9 | B10: ='План месяцев F1'!C10 -> 200 | C10: =B10*'Допущения F1'!$B$4 -> 30 | D10: =C10*'Допущения F1'!$B$5 -> 12 | E10: =D10*'Допущения F1'!$B$6 -> 1.8 | F10: ='План месяцев F1'!D10 -> 0 | G10: =H9*'Допущения F1'!$B$7 -> 0.409262 | H10: =H9-G10+E10+F10 -> 8.2117713 | I10: =(H9+H10)/2 -> 7.5164023 | J10: ='Допущения F1'!$B$8 -> 9900 | K10: =H10*J10 -> 81296.536 | L10: ='План месяцев F1'!E10*'Допущения F1'!$B$17 -> 0 | M10: ='План месяцев F1'!F10*'Допущения F1'!$B$16 -> 0 | N10: =I10*J10+L10+M10 -> 74412.383 | O10: =(I10*'Допущения F1'!$B$9+'План месяцев F1'!F10)*('Допущения F1'!$B$10+'План месяцев F1'!G10*'Допущения F1'!$B$11*'Допущения F1'!$B$12)+F10*J10*'Допущения F1'!$B$15+L10*'План месяцев F1'!G10 -> 56373.017 | P10: =N10-O10 -> 18039.366 | Q10: ='План месяцев F1'!H10+'Допущения F1'!$B$18 -> 50000 | R10: =U10*'Допущения F1'!$B$14 -> 4066.9475 | S10: =MAX(0,'Допущения F1'!$B$19-'Допущения F1'!$B$18) -> 60000 | T10: =P10-Q10-R10-S10 -> -96027.582 | U10: =N10*(1-'Допущения F1'!$B$13)+(N9)*'Допущения F1'!$B$13 -> 67782.459 | V10: =O10+Q10+R10 -> 110439.96 | W10: ='План месяцев F1'!I10 -> 0 | X10: =X9+U10-V10+W10 -> -223160.91 | Y10: =IF(X10<Q10*'Допущения F1'!$B$20,"НИЖЕ РЕЗЕРВА","РЕЗЕРВ ЕСТЬ") -> НИЖЕ РЕЗЕРВА
A11: ='План месяцев F1'!A11 -> 10 | B11: ='План месяцев F1'!C11 -> 220 | C11: =B11*'Допущения F1'!$B$4 -> 33 | D11: =C11*'Допущения F1'!$B$5 -> 13.2 | E11: =D11*'Допущения F1'!$B$6 -> 1.98 | F11: ='План месяцев F1'!D11 -> 0 | G11: =H10*'Допущения F1'!$B$7 -> 0.49270628 | H11: =H10-G11+E11+F11 -> 9.699065 | I11: =(H10+H11)/2 -> 8.9554182 | J11: ='Допущения F1'!$B$8 -> 9900 | K11: =H11*J11 -> 96020.744 | L11: ='План месяцев F1'!E11*'Допущения F1'!$B$17 -> 0 | M11: ='План месяцев F1'!F11*'Допущения F1'!$B$16 -> 0 | N11: =I11*J11+L11+M11 -> 88658.64 | O11: =(I11*'Допущения F1'!$B$9+'План месяцев F1'!F11)*('Допущения F1'!$B$10+'План месяцев F1'!G11*'Допущения F1'!$B$11*'Допущения F1'!$B$12)+F11*J11*'Допущения F1'!$B$15+L11*'План месяцев F1'!G11 -> 67165.636 | P11: =N11-O11 -> 21493.004 | Q11: ='План месяцев F1'!H11+'Допущения F1'!$B$18 -> 60000 | R11: =U11*'Допущения F1'!$B$14 -> 4892.1307 | S11: =MAX(0,'Допущения F1'!$B$19-'Допущения F1'!$B$18) -> 60000 | T11: =P11-Q11-R11-S11 -> -103399.13 | U11: =N11*(1-'Допущения F1'!$B$13)+(N10)*'Допущения F1'!$B$13 -> 81535.511 | V11: =O11+Q11+R11 -> 132057.77 | W11: ='План месяцев F1'!I11 -> 0 | X11: =X10+U11-V11+W11 -> -273683.16 | Y11: =IF(X11<Q11*'Допущения F1'!$B$20,"НИЖЕ РЕЗЕРВА","РЕЗЕРВ ЕСТЬ") -> НИЖЕ РЕЗЕРВА
A12: ='План месяцев F1'!A12 -> 11 | B12: ='План месяцев F1'!C12 -> 240 | C12: =B12*'Допущения F1'!$B$4 -> 36 | D12: =C12*'Допущения F1'!$B$5 -> 14.4 | E12: =D12*'Допущения F1'!$B$6 -> 2.16 | F12: ='План месяцев F1'!D12 -> 0 | G12: =H11*'Допущения F1'!$B$7 -> 0.5819439 | H12: =H11-G12+E12+F12 -> 11.277121 | I12: =(H11+H12)/2 -> 10.488093 | J12: ='Допущения F1'!$B$8 -> 9900 | K12: =H12*J12 -> 111643.5 | L12: ='План месяцев F1'!E12*'Допущения F1'!$B$17 -> 0 | M12: ='План месяцев F1'!F12*'Допущения F1'!$B$16 -> 0 | N12: =I12*J12+L12+M12 -> 103832.12 | O12: =(I12*'Допущения F1'!$B$9+'План месяцев F1'!F12)*('Допущения F1'!$B$10+'План месяцев F1'!G12*'Допущения F1'!$B$11*'Допущения F1'!$B$12)+F12*J12*'Допущения F1'!$B$15+L12*'План месяцев F1'!G12 -> 78660.698 | P12: =N12-O12 -> 25171.423 | Q12: ='План месяцев F1'!H12+'Допущения F1'!$B$18 -> 60000 | R12: =U12*'Допущения F1'!$B$14 -> 5774.7228 | S12: =MAX(0,'Допущения F1'!$B$19-'Допущения F1'!$B$18) -> 60000 | T12: =P12-Q12-R12-S12 -> -100603.3 | U12: =N12*(1-'Допущения F1'!$B$13)+(N11)*'Допущения F1'!$B$13 -> 96245.381 | V12: =O12+Q12+R12 -> 144435.42 | W12: ='План месяцев F1'!I12 -> 0 | X12: =X11+U12-V12+W12 -> -321873.2 | Y12: =IF(X12<Q12*'Допущения F1'!$B$20,"НИЖЕ РЕЗЕРВА","РЕЗЕРВ ЕСТЬ") -> НИЖЕ РЕЗЕРВА
A13: ='План месяцев F1'!A13 -> 12 | B13: ='План месяцев F1'!C13 -> 260 | C13: =B13*'Допущения F1'!$B$4 -> 39 | D13: =C13*'Допущения F1'!$B$5 -> 15.6 | E13: =D13*'Допущения F1'!$B$6 -> 2.34 | F13: ='План месяцев F1'!D13 -> 0 | G13: =H12*'Допущения F1'!$B$7 -> 0.67662727 | H13: =H12-G13+E13+F13 -> 12.940494 | I13: =(H12+H13)/2 -> 12.108807 | J13: ='Допущения F1'!$B$8 -> 9900 | K13: =H13*J13 -> 128110.89 | L13: ='План месяцев F1'!E13*'Допущения F1'!$B$17 -> 0 | M13: ='План месяцев F1'!F13*'Допущения F1'!$B$16 -> 0 | N13: =I13*J13+L13+M13 -> 119877.19 | O13: =(I13*'Допущения F1'!$B$9+'План месяцев F1'!F13)*('Допущения F1'!$B$10+'План месяцев F1'!G13*'Допущения F1'!$B$11*'Допущения F1'!$B$12)+F13*J13*'Допущения F1'!$B$15+L13*'План месяцев F1'!G13 -> 90816.056 | P13: =N13-O13 -> 29061.138 | Q13: ='План месяцев F1'!H13+'Допущения F1'!$B$18 -> 60000 | R13: =U13*'Допущения F1'!$B$14 -> 6711.2795 | S13: =MAX(0,'Допущения F1'!$B$19-'Допущения F1'!$B$18) -> 60000 | T13: =P13-Q13-R13-S13 -> -97650.141 | U13: =N13*(1-'Допущения F1'!$B$13)+(N12)*'Допущения F1'!$B$13 -> 111854.66 | V13: =O13+Q13+R13 -> 157527.34 | W13: ='План месяцев F1'!I13 -> 0 | X13: =X12+U13-V13+W13 -> -367545.88 | Y13: =IF(X13<Q13*'Допущения F1'!$B$20,"НИЖЕ РЕЗЕРВА","РЕЗЕРВ ЕСТЬ") -> НИЖЕ РЕЗЕРВА

Sheet Рабочий F1
A1: Мес. | B1: Контакты | C1: Ответы | D1: Демо | E1: Новые прямые | F1: Новые партн. | G1: Отток, клиентов | H1: Клиенты на конец | I1: Средние активные | J1: ARPU, руб. | K1: MRR конец, руб. | L1: Разовые пилоты | M1: Разовые документы | N1: Начислено всего | O1: Прямые затраты | P1: Вклад до фикс. | Q1: Фикс. выплаты | R1: Налоговый резерв | S1: Неопл. труд основ. | T1: Экон. результат | U1: Денежные поступления | V1: Денежные расходы | W1: Подтвержд. деньги | X1: Касса на конец | Y1: Запас кассы
A2: ='План месяцев F1'!A2 -> 1 | B2: ='План месяцев F1'!C2 -> 40 | C2: =B2*'Допущения F1'!$C$4 -> 10 | D2: =C2*'Допущения F1'!$C$5 -> 5 | E2: =D2*'Допущения F1'!$C$6 -> 1.25 | F2: ='План месяцев F1'!D2 -> 0 | G2: =0*'Допущения F1'!$C$7 -> 0 | H2: =0-G2+E2+F2 -> 1.25 | I2: =(0+H2)/2 -> 0.625 | J2: ='Допущения F1'!$C$8 -> 14900 | K2: =H2*J2 -> 18625 | L2: ='План месяцев F1'!E2*'Допущения F1'!$C$17 -> 0 | M2: ='План месяцев F1'!F2*'Допущения F1'!$C$16 -> 0 | N2: =I2*J2+L2+M2 -> 9312.5 | O2: =(I2*'Допущения F1'!$C$9+'План месяцев F1'!F2)*('Допущения F1'!$C$10+'План месяцев F1'!G2*'Допущения F1'!$C$11*'Допущения F1'!$C$12)+F2*J2*'Допущения F1'!$C$15+L2*'План месяцев F1'!G2 -> 4687.5 | P2: =N2-O2 -> 4625 | Q2: ='План месяцев F1'!H2+'Допущения F1'!$C$18 -> 30000 | R2: =U2*'Допущения F1'!$C$14 -> 391.125 | S2: =MAX(0,'Допущения F1'!$C$19-'Допущения F1'!$C$18) -> 60000 | T2: =P2-Q2-R2-S2 -> -85766.125 | U2: =N2*(1-'Допущения F1'!$C$13)+(0)*'Допущения F1'!$C$13 -> 6518.75 | V2: =O2+Q2+R2 -> 35078.625 | W2: ='План месяцев F1'!I2 -> 0 | X2: ='Допущения F1'!$C$2-'Допущения F1'!$C$3+U2-V2+W2 -> 90440.125 | Y2: =IF(X2<Q2*'Допущения F1'!$C$20,"НИЖЕ РЕЗЕРВА","РЕЗЕРВ ЕСТЬ") -> РЕЗЕРВ ЕСТЬ
A3: ='План месяцев F1'!A3 -> 2 | B3: ='План месяцев F1'!C3 -> 60 | C3: =B3*'Допущения F1'!$C$4 -> 15 | D3: =C3*'Допущения F1'!$C$5 -> 7.5 | E3: =D3*'Допущения F1'!$C$6 -> 1.875 | F3: ='План месяцев F1'!D3 -> 0 | G3: =H2*'Допущения F1'!$C$7 -> 0.05 | H3: =H2-G3+E3+F3 -> 3.075 | I3: =(H2+H3)/2 -> 2.1625 | J3: ='Допущения F1'!$C$8 -> 14900 | K3: =H3*J3 -> 45817.5 | L3: ='План месяцев F1'!E3*'Допущения F1'!$C$17 -> 0 | M3: ='План месяцев F1'!F3*'Допущения F1'!$C$16 -> 0 | N3: =I3*J3+L3+M3 -> 32221.25 | O3: =(I3*'Допущения F1'!$C$9+'План месяцев F1'!F3)*('Допущения F1'!$C$10+'План месяцев F1'!G3*'Допущения F1'!$C$11*'Допущения F1'!$C$12)+F3*J3*'Допущения F1'!$C$15+L3*'План месяцев F1'!G3 -> 16218.75 | P3: =N3-O3 -> 16002.5 | Q3: ='План месяцев F1'!H3+'Допущения F1'!$C$18 -> 30000 | R3: =U3*'Допущения F1'!$C$14 -> 1520.9175 | S3: =MAX(0,'Допущения F1'!$C$19-'Допущения F1'!$C$18) -> 60000 | T3: =P3-Q3-R3-S3 -> -75518.417 | U3: =N3*(1-'Допущения F1'!$C$13)+(N2)*'Допущения F1'!$C$13 -> 25348.625 | V3: =O3+Q3+R3 -> 47739.668 | W3: ='План месяцев F1'!I3 -> 0 | X3: =X2+U3-V3+W3 -> 68049.083 | Y3: =IF(X3<Q3*'Допущения F1'!$C$20,"НИЖЕ РЕЗЕРВА","РЕЗЕРВ ЕСТЬ") -> НИЖЕ РЕЗЕРВА
A4: ='План месяцев F1'!A4 -> 3 | B4: ='План месяцев F1'!C4 -> 80 | C4: =B4*'Допущения F1'!$C$4 -> 20 | D4: =C4*'Допущения F1'!$C$5 -> 10 | E4: =D4*'Допущения F1'!$C$6 -> 2.5 | F4: ='План месяцев F1'!D4 -> 0 | G4: =H3*'Допущения F1'!$C$7 -> 0.123 | H4: =H3-G4+E4+F4 -> 5.452 | I4: =(H3+H4)/2 -> 4.2635 | J4: ='Допущения F1'!$C$8 -> 14900 | K4: =H4*J4 -> 81234.8 | L4: ='План месяцев F1'!E4*'Допущения F1'!$C$17 -> 0 | M4: ='План месяцев F1'!F4*'Допущения F1'!$C$16 -> 0 | N4: =I4*J4+L4+M4 -> 63526.15 | O4: =(I4*'Допущения F1'!$C$9+'План месяцев F1'!F4)*('Допущения F1'!$C$10+'План месяцев F1'!G4*'Допущения F1'!$C$11*'Допущения F1'!$C$12)+F4*J4*'Допущения F1'!$C$15+L4*'План месяцев F1'!G4 -> 31976.25 | P4: =N4-O4 -> 31549.9 | Q4: ='План месяцев F1'!H4+'Допущения F1'!$C$18 -> 30000 | R4: =U4*'Допущения F1'!$C$14 -> 3248.0808 | S4: =MAX(0,'Допущения F1'!$C$19-'Допущения F1'!$C$18) -> 60000 | T4: =P4-Q4-R4-S4 -> -61698.181 | U4: =N4*(1-'Допущения F1'!$C$13)+(N3)*'Допущения F1'!$C$13 -> 54134.68 | V4: =O4+Q4+R4 -> 65224.331 | W4: ='План месяцев F1'!I4 -> 0 | X4: =X3+U4-V4+W4 -> 56959.432 | Y4: =IF(X4<Q4*'Допущения F1'!$C$20,"НИЖЕ РЕЗЕРВА","РЕЗЕРВ ЕСТЬ") -> НИЖЕ РЕЗЕРВА
A5: ='План месяцев F1'!A5 -> 4 | B5: ='План месяцев F1'!C5 -> 100 | C5: =B5*'Допущения F1'!$C$4 -> 25 | D5: =C5*'Допущения F1'!$C$5 -> 12.5 | E5: =D5*'Допущения F1'!$C$6 -> 3.125 | F5: ='План месяцев F1'!D5 -> 0 | G5: =H4*'Допущения F1'!$C$7 -> 0.21808 | H5: =H4-G5+E5+F5 -> 8.35892 | I5: =(H4+H5)/2 -> 6.90546 | J5: ='Допущения F1'!$C$8 -> 14900 | K5: =H5*J5 -> 124547.91 | L5: ='План месяцев F1'!E5*'Допущения F1'!$C$17 -> 0 | M5: ='План месяцев F1'!F5*'Допущения F1'!$C$16 -> 0 | N5: =I5*J5+L5+M5 -> 102891.35 | O5: =(I5*'Допущения F1'!$C$9+'План месяцев F1'!F5)*('Допущения F1'!$C$10+'План месяцев F1'!G5*'Допущения F1'!$C$11*'Допущения F1'!$C$12)+F5*J5*'Допущения F1'!$C$15+L5*'План месяцев F1'!G5 -> 51790.95 | P5: =N5-O5 -> 51100.404 | Q5: ='План месяцев F1'!H5+'Допущения F1'!$C$18 -> 40000 | R5: =U5*'Допущения F1'!$C$14 -> 5464.9076 | S5: =MAX(0,'Допущения F1'!$C$19-'Допущения F1'!$C$18) -> 60000 | T5: =P5-Q5-R5-S5 -> -54364.504 | U5: =N5*(1-'Допущения F1'!$C$13)+(N4)*'Допущения F1'!$C$13 -> 91081.793 | V5: =O5+Q5+R5 -> 97255.858 | W5: ='План месяцев F1'!I5 -> 0 | X5: =X4+U5-V5+W5 -> 50785.367 | Y5: =IF(X5<Q5*'Допущения F1'!$C$20,"НИЖЕ РЕЗЕРВА","РЕЗЕРВ ЕСТЬ") -> НИЖЕ РЕЗЕРВА
A6: ='План месяцев F1'!A6 -> 5 | B6: ='План месяцев F1'!C6 -> 120 | C6: =B6*'Допущения F1'!$C$4 -> 30 | D6: =C6*'Допущения F1'!$C$5 -> 15 | E6: =D6*'Допущения F1'!$C$6 -> 3.75 | F6: ='План месяцев F1'!D6 -> 0 | G6: =H5*'Допущения F1'!$C$7 -> 0.3343568 | H6: =H5-G6+E6+F6 -> 11.774563 | I6: =(H5+H6)/2 -> 10.066742 | J6: ='Допущения F1'!$C$8 -> 14900 | K6: =H6*J6 -> 175440.99 | L6: ='План месяцев F1'!E6*'Допущения F1'!$C$17 -> 0 | M6: ='План месяцев F1'!F6*'Допущения F1'!$C$16 -> 0 | N6: =I6*J6+L6+M6 -> 149994.45 | O6: =(I6*'Допущения F1'!$C$9+'План месяцев F1'!F6)*('Допущения F1'!$C$10+'План месяцев F1'!G6*'Допущения F1'!$C$11*'Допущения F1'!$C$12)+F6*J6*'Допущения F1'!$C$15+L6*'План месяцев F1'!G6 -> 75500.562 | P6: =N6-O6 -> 74493.888 | Q6: ='План месяцев F1'!H6+'Допущения F1'!$C$18 -> 40000 | R6: =U6*'Допущения F1'!$C$14 -> 8151.8113 | S6: =MAX(0,'Допущения F1'!$C$19-'Допущения F1'!$C$18) -> 60000 | T6: =P6-Q6-R6-S6 -> -33657.923 | U6: =N6*(1-'Допущения F1'!$C$13)+(N5)*'Допущения F1'!$C$13 -> 135863.52 | V6: =O6+Q6+R6 -> 123652.37 | W6: ='План месяцев F1'!I6 -> 0 | X6: =X5+U6-V6+W6 -> 62996.515 | Y6: =IF(X6<Q6*'Допущения F1'!$C$20,"НИЖЕ РЕЗЕРВА","РЕЗЕРВ ЕСТЬ") -> НИЖЕ РЕЗЕРВА
A7: ='План месяцев F1'!A7 -> 6 | B7: ='План месяцев F1'!C7 -> 140 | C7: =B7*'Допущения F1'!$C$4 -> 35 | D7: =C7*'Допущения F1'!$C$5 -> 17.5 | E7: =D7*'Допущения F1'!$C$6 -> 4.375 | F7: ='План месяцев F1'!D7 -> 0 | G7: =H6*'Допущения F1'!$C$7 -> 0.47098253 | H7: =H6-G7+E7+F7 -> 15.678581 | I7: =(H6+H7)/2 -> 13.726572 | J7: ='Допущения F1'!$C$8 -> 14900 | K7: =H7*J7 -> 233610.85 | L7: ='План месяцев F1'!E7*'Допущения F1'!$C$17 -> 0 | M7: ='План месяцев F1'!F7*'Допущения F1'!$C$16 -> 0 | N7: =I7*J7+L7+M7 -> 204525.92 | O7: =(I7*'Допущения F1'!$C$9+'План месяцев F1'!F7)*('Допущения F1'!$C$10+'План месяцев F1'!G7*'Допущения F1'!$C$11*'Допущения F1'!$C$12)+F7*J7*'Допущения F1'!$C$15+L7*'План месяцев F1'!G7 -> 102949.29 | P7: =N7-O7 -> 101576.63 | Q7: ='План месяцев F1'!H7+'Допущения F1'!$C$18 -> 40000 | R7: =U7*'Допущения F1'!$C$14 -> 11289.989 | S7: =MAX(0,'Допущения F1'!$C$19-'Допущения F1'!$C$18) -> 60000 | T7: =P7-Q7-R7-S7 -> -9713.3565 | U7: =N7*(1-'Допущения F1'!$C$13)+(N6)*'Допущения F1'!$C$13 -> 188166.48 | V7: =O7+Q7+R7 -> 154239.28 | W7: ='План месяцев F1'!I7 -> 0 | X7: =X6+U7-V7+W7 -> 96923.717 | Y7: =IF(X7<Q7*'Допущения F1'!$C$20,"НИЖЕ РЕЗЕРВА","РЕЗЕРВ ЕСТЬ") -> НИЖЕ РЕЗЕРВА
A8: ='План месяцев F1'!A8 -> 7 | B8: ='План месяцев F1'!C8 -> 160 | C8: =B8*'Допущения F1'!$C$4 -> 40 | D8: =C8*'Допущения F1'!$C$5 -> 20 | E8: =D8*'Допущения F1'!$C$6 -> 5 | F8: ='План месяцев F1'!D8 -> 0 | G8: =H7*'Допущения F1'!$C$7 -> 0.62714323 | H8: =H7-G8+E8+F8 -> 20.051437 | I8: =(H7+H8)/2 -> 17.865009 | J8: ='Допущения F1'!$C$8 -> 14900 | K8: =H8*J8 -> 298766.42 | L8: ='План месяцев F1'!E8*'Допущения F1'!$C$17 -> 0 | M8: ='План месяцев F1'!F8*'Допущения F1'!$C$16 -> 0 | N8: =I8*J8+L8+M8 -> 266188.63 | O8: =(I8*'Допущения F1'!$C$9+'План месяцев F1'!F8)*('Допущения F1'!$C$10+'План месяцев F1'!G8*'Допущения F1'!$C$11*'Допущения F1'!$C$12)+F8*J8*'Допущения F1'!$C$15+L8*'План месяцев F1'!G8 -> 133987.57 | P8: =N8-O8 -> 132201.07 | Q8: ='План месяцев F1'!H8+'Допущения F1'!$C$18 -> 50000 | R8: =U8*'Допущения F1'!$C$14 -> 14861.389 | S8: =MAX(0,'Допущения F1'!$C$19-'Допущения F1'!$C$18) -> 60000 | T8: =P8-Q8-R8-S8 -> 7339.6778 | U8: =N8*(1-'Допущения F1'!$C$13)+(N7)*'Допущения F1'!$C$13 -> 247689.82 | V8: =O8+Q8+R8 -> 198848.96 | W8: ='План месяцев F1'!I8 -> 0 | X8: =X7+U8-V8+W8 -> 145764.58 | Y8: =IF(X8<Q8*'Допущения F1'!$C$20,"НИЖЕ РЕЗЕРВА","РЕЗЕРВ ЕСТЬ") -> НИЖЕ РЕЗЕРВА
A9: ='План месяцев F1'!A9 -> 8 | B9: ='План месяцев F1'!C9 -> 180 | C9: =B9*'Допущения F1'!$C$4 -> 45 | D9: =C9*'Допущения F1'!$C$5 -> 22.5 | E9: =D9*'Допущения F1'!$C$6 -> 5.625 | F9: ='План месяцев F1'!D9 -> 0 | G9: =H8*'Допущения F1'!$C$7 -> 0.8020575 | H9: =H8-G9+E9+F9 -> 24.87438 | I9: =(H8+H9)/2 -> 22.462909 | J9: ='Допущения F1'!$C$8 -> 14900 | K9: =H9*J9 -> 370628.26 | L9: ='План месяцев F1'!E9*'Допущения F1'!$C$17 -> 0 | M9: ='План месяцев F1'!F9*'Допущения F1'!$C$16 -> 0 | N9: =I9*J9+L9+M9 -> 334697.34 | O9: =(I9*'Допущения F1'!$C$9+'План месяцев F1'!F9)*('Допущения F1'!$C$10+'План месяцев F1'!G9*'Допущения F1'!$C$11*'Допущения F1'!$C$12)+F9*J9*'Допущения F1'!$C$15+L9*'План месяцев F1'!G9 -> 168471.82 | P9: =N9-O9 -> 166225.52 | Q9: ='План месяцев F1'!H9+'Допущения F1'!$C$18 -> 50000 | R9: =U9*'Допущения F1'!$C$14 -> 18848.684 | S9: =MAX(0,'Допущения F1'!$C$19-'Допущения F1'!$C$18) -> 60000 | T9: =P9-Q9-R9-S9 -> 37376.841 | U9: =N9*(1-'Допущения F1'!$C$13)+(N8)*'Допущения F1'!$C$13 -> 314144.73 | V9: =O9+Q9+R9 -> 237320.5 | W9: ='План месяцев F1'!I9 -> 0 | X9: =X8+U9-V9+W9 -> 222588.81 | Y9: =IF(X9<Q9*'Допущения F1'!$C$20,"НИЖЕ РЕЗЕРВА","РЕЗЕРВ ЕСТЬ") -> РЕЗЕРВ ЕСТЬ
A10: ='План месяцев F1'!A10 -> 9 | B10: ='План месяцев F1'!C10 -> 200 | C10: =B10*'Допущения F1'!$C$4 -> 50 | D10: =C10*'Допущения F1'!$C$5 -> 25 | E10: =D10*'Допущения F1'!$C$6 -> 6.25 | F10: ='План месяцев F1'!D10 -> 0 | G10: =H9*'Допущения F1'!$C$7 -> 0.9949752 | H10: =H9-G10+E10+F10 -> 30.129405 | I10: =(H9+H10)/2 -> 27.501892 | J10: ='Допущения F1'!$C$8 -> 14900 | K10: =H10*J10 -> 448928.13 | L10: ='План месяцев F1'!E10*'Допущения F1'!$C$17 -> 0 | M10: ='План месяцев F1'!F10*'Допущения F1'!$C$16 -> 0 | N10: =I10*J10+L10+M10 -> 409778.2 | O10: =(I10*'Допущения F1'!$C$9+'План месяцев F1'!F10)*('Допущения F1'!$C$10+'План месяцев F1'!G10*'Допущения F1'!$C$11*'Допущения F1'!$C$12)+F10*J10*'Допущения F1'!$C$15+L10*'План месяцев F1'!G10 -> 206264.19 | P10: =N10-O10 -> 203514 | Q10: ='План месяцев F1'!H10+'Допущения F1'!$C$18 -> 50000 | R10: =U10*'Допущения F1'!$C$14 -> 23235.236 | S10: =MAX(0,'Допущения F1'!$C$19-'Допущения F1'!$C$18) -> 60000 | T10: =P10-Q10-R10-S10 -> 70278.767 | U10: =N10*(1-'Допущения F1'!$C$13)+(N9)*'Допущения F1'!$C$13 -> 387253.94 | V10: =O10+Q10+R10 -> 279499.43 | W10: ='План месяцев F1'!I10 -> 0 | X10: =X9+U10-V10+W10 -> 330343.32 | Y10: =IF(X10<Q10*'Допущения F1'!$C$20,"НИЖЕ РЕЗЕРВА","РЕЗЕРВ ЕСТЬ") -> РЕЗЕРВ ЕСТЬ
A11: ='План месяцев F1'!A11 -> 10 | B11: ='План месяцев F1'!C11 -> 220 | C11: =B11*'Допущения F1'!$C$4 -> 55 | D11: =C11*'Допущения F1'!$C$5 -> 27.5 | E11: =D11*'Допущения F1'!$C$6 -> 6.875 | F11: ='План месяцев F1'!D11 -> 0 | G11: =H10*'Допущения F1'!$C$7 -> 1.2051762 | H11: =H10-G11+E11+F11 -> 35.799229 | I11: =(H10+H11)/2 -> 32.964317 | J11: ='Допущения F1'!$C$8 -> 14900 | K11: =H11*J11 -> 533408.51 | L11: ='План месяцев F1'!E11*'Допущения F1'!$C$17 -> 0 | M11: ='План месяцев F1'!F11*'Допущения F1'!$C$16 -> 0 | N11: =I11*J11+L11+M11 -> 491168.32 | O11: =(I11*'Допущения F1'!$C$9+'План месяцев F1'!F11)*('Допущения F1'!$C$10+'План месяцев F1'!G11*'Допущения F1'!$C$11*'Допущения F1'!$C$12)+F11*J11*'Допущения F1'!$C$15+L11*'План месяцев F1'!G11 -> 247232.37 | P11: =N11-O11 -> 243935.94 | Q11: ='План месяцев F1'!H11+'Допущения F1'!$C$18 -> 60000 | R11: =U11*'Допущения F1'!$C$14 -> 28005.077 | S11: =MAX(0,'Допущения F1'!$C$19-'Допущения F1'!$C$18) -> 60000 | T11: =P11-Q11-R11-S11 -> 95930.866 | U11: =N11*(1-'Допущения F1'!$C$13)+(N10)*'Допущения F1'!$C$13 -> 466751.28 | V11: =O11+Q11+R11 -> 335237.45 | W11: ='План месяцев F1'!I11 -> 0 | X11: =X10+U11-V11+W11 -> 461857.15 | Y11: =IF(X11<Q11*'Допущения F1'!$C$20,"НИЖЕ РЕЗЕРВА","РЕЗЕРВ ЕСТЬ") -> РЕЗЕРВ ЕСТЬ
A12: ='План месяцев F1'!A12 -> 11 | B12: ='План месяцев F1'!C12 -> 240 | C12: =B12*'Допущения F1'!$C$4 -> 60 | D12: =C12*'Допущения F1'!$C$5 -> 30 | E12: =D12*'Допущения F1'!$C$6 -> 7.5 | F12: ='План месяцев F1'!D12 -> 0 | G12: =H11*'Допущения F1'!$C$7 -> 1.4319691 | H12: =H11-G12+E12+F12 -> 41.867259 | I12: =(H11+H12)/2 -> 38.833244 | J12: ='Допущения F1'!$C$8 -> 14900 | K12: =H12*J12 -> 623822.17 | L12: ='План месяцев F1'!E12*'Допущения F1'!$C$17 -> 0 | M12: ='План месяцев F1'!F12*'Допущения F1'!$C$16 -> 0 | N12: =I12*J12+L12+M12 -> 578615.34 | O12: =(I12*'Допущения F1'!$C$9+'План месяцев F1'!F12)*('Допущения F1'!$C$10+'План месяцев F1'!G12*'Допущения F1'!$C$11*'Допущения F1'!$C$12)+F12*J12*'Допущения F1'!$C$15+L12*'План месяцев F1'!G12 -> 291249.33 | P12: =N12-O12 -> 287366.01 | Q12: ='План месяцев F1'!H12+'Допущения F1'!$C$18 -> 60000 | R12: =U12*'Допущения F1'!$C$14 -> 33142.874 | S12: =MAX(0,'Допущения F1'!$C$19-'Допущения F1'!$C$18) -> 60000 | T12: =P12-Q12-R12-S12 -> 134223.13 | U12: =N12*(1-'Допущения F1'!$C$13)+(N11)*'Допущения F1'!$C$13 -> 552381.23 | V12: =O12+Q12+R12 -> 384392.2 | W12: ='План месяцев F1'!I12 -> 0 | X12: =X11+U12-V12+W12 -> 629846.18 | Y12: =IF(X12<Q12*'Допущения F1'!$C$20,"НИЖЕ РЕЗЕРВА","РЕЗЕРВ ЕСТЬ") -> РЕЗЕРВ ЕСТЬ
A13: ='План месяцев F1'!A13 -> 12 | B13: ='План месяцев F1'!C13 -> 260 | C13: =B13*'Допущения F1'!$C$4 -> 65 | D13: =C13*'Допущения F1'!$C$5 -> 32.5 | E13: =D13*'Допущения F1'!$C$6 -> 8.125 | F13: ='План месяцев F1'!D13 -> 0 | G13: =H12*'Допущения F1'!$C$7 -> 1.6746904 | H13: =H12-G13+E13+F13 -> 48.317569 | I13: =(H12+H13)/2 -> 45.092414 | J13: ='Допущения F1'!$C$8 -> 14900 | K13: =H13*J13 -> 719931.78 | L13: ='План месяцев F1'!E13*'Допущения F1'!$C$17 -> 0 | M13: ='План месяцев F1'!F13*'Допущения F1'!$C$16 -> 0 | N13: =I13*J13+L13+M13 -> 671876.97 | O13: =(I13*'Допущения F1'!$C$9+'План месяцев F1'!F13)*('Допущения F1'!$C$10+'План месяцев F1'!G13*'Допущения F1'!$C$11*'Допущения F1'!$C$12)+F13*J13*'Допущения F1'!$C$15+L13*'План месяцев F1'!G13 -> 338193.11 | P13: =N13-O13 -> 333683.87 | Q13: ='План месяцев F1'!H13+'Допущения F1'!$C$18 -> 60000 | R13: =U13*'Допущения F1'!$C$14 -> 38633.909 | S13: =MAX(0,'Допущения F1'!$C$19-'Допущения F1'!$C$18) -> 60000 | T13: =P13-Q13-R13-S13 -> 175049.96 | U13: =N13*(1-'Допущения F1'!$C$13)+(N12)*'Допущения F1'!$C$13 -> 643898.48 | V13: =O13+Q13+R13 -> 436827.02 | W13: ='План месяцев F1'!I13 -> 0 | X13: =X12+U13-V13+W13 -> 836917.64 | Y13: =IF(X13<Q13*'Допущения F1'!$C$20,"НИЖЕ РЕЗЕРВА","РЕЗЕРВ ЕСТЬ") -> РЕЗЕРВ ЕСТЬ

Sheet Сильный F1
A1: Мес. | B1: Контакты | C1: Ответы | D1: Демо | E1: Новые прямые | F1: Новые партн. | G1: Отток, клиентов | H1: Клиенты на конец | I1: Средние активные | J1: ARPU, руб. | K1: MRR конец, руб. | L1: Разовые пилоты | M1: Разовые документы | N1: Начислено всего | O1: Прямые затраты | P1: Вклад до фикс. | Q1: Фикс. выплаты | R1: Налоговый резерв | S1: Неопл. труд основ. | T1: Экон. результат | U1: Денежные поступления | V1: Денежные расходы | W1: Подтвержд. деньги | X1: Касса на конец | Y1: Запас кассы
A2: ='План месяцев F1'!A2 -> 1 | B2: ='План месяцев F1'!C2 -> 40 | C2: =B2*'Допущения F1'!$D$4 -> 14 | D2: =C2*'Допущения F1'!$D$5 -> 8.4 | E2: =D2*'Допущения F1'!$D$6 -> 2.52 | F2: ='План месяцев F1'!D2 -> 0 | G2: =0*'Допущения F1'!$D$7 -> 0 | H2: =0-G2+E2+F2 -> 2.52 | I2: =(0+H2)/2 -> 1.26 | J2: ='Допущения F1'!$D$8 -> 19900 | K2: =H2*J2 -> 50148 | L2: ='План месяцев F1'!E2*'Допущения F1'!$D$17 -> 0 | M2: ='План месяцев F1'!F2*'Допущения F1'!$D$16 -> 0 | N2: =I2*J2+L2+M2 -> 25074 | O2: =(I2*'Допущения F1'!$D$9+'План месяцев F1'!F2)*('Допущения F1'!$D$10+'План месяцев F1'!G2*'Допущения F1'!$D$11*'Допущения F1'!$D$12)+F2*J2*'Допущения F1'!$D$15+L2*'План месяцев F1'!G2 -> 9450 | P2: =N2-O2 -> 15624 | Q2: ='План месяцев F1'!H2+'Допущения F1'!$D$18 -> 30000 | R2: =U2*'Допущения F1'!$D$14 -> 1353.996 | S2: =MAX(0,'Допущения F1'!$D$19-'Допущения F1'!$D$18) -> 60000 | T2: =P2-Q2-R2-S2 -> -75729.996 | U2: =N2*(1-'Допущения F1'!$D$13)+(0)*'Допущения F1'!$D$13 -> 22566.6 | V2: =O2+Q2+R2 -> 40803.996 | W2: ='План месяцев F1'!I2 -> 0 | X2: ='Допущения F1'!$D$2-'Допущения F1'!$D$3+U2-V2+W2 -> 100762.6 | Y2: =IF(X2<Q2*'Допущения F1'!$D$20,"НИЖЕ РЕЗЕРВА","РЕЗЕРВ ЕСТЬ") -> РЕЗЕРВ ЕСТЬ
A3: ='План месяцев F1'!A3 -> 2 | B3: ='План месяцев F1'!C3 -> 60 | C3: =B3*'Допущения F1'!$D$4 -> 21 | D3: =C3*'Допущения F1'!$D$5 -> 12.6 | E3: =D3*'Допущения F1'!$D$6 -> 3.78 | F3: ='План месяцев F1'!D3 -> 0 | G3: =H2*'Допущения F1'!$D$7 -> 0.0756 | H3: =H2-G3+E3+F3 -> 6.2244 | I3: =(H2+H3)/2 -> 4.3722 | J3: ='Допущения F1'!$D$8 -> 19900 | K3: =H3*J3 -> 123865.56 | L3: ='План месяцев F1'!E3*'Допущения F1'!$D$17 -> 0 | M3: ='План месяцев F1'!F3*'Допущения F1'!$D$16 -> 0 | N3: =I3*J3+L3+M3 -> 87006.78 | O3: =(I3*'Допущения F1'!$D$9+'План месяцев F1'!F3)*('Допущения F1'!$D$10+'План месяцев F1'!G3*'Допущения F1'!$D$11*'Допущения F1'!$D$12)+F3*J3*'Допущения F1'!$D$15+L3*'План месяцев F1'!G3 -> 32791.5 | P3: =N3-O3 -> 54215.28 | Q3: ='План месяцев F1'!H3+'Допущения F1'!$D$18 -> 30000 | R3: =U3*'Допущения F1'!$D$14 -> 4848.8101 | S3: =MAX(0,'Допущения F1'!$D$19-'Допущения F1'!$D$18) -> 60000 | T3: =P3-Q3-R3-S3 -> -40633.53 | U3: =N3*(1-'Допущения F1'!$D$13)+(N2)*'Допущения F1'!$D$13 -> 80813.502 | V3: =O3+Q3+R3 -> 67640.31 | W3: ='План месяцев F1'!I3 -> 0 | X3: =X2+U3-V3+W3 -> 113935.8 | Y3: =IF(X3<Q3*'Допущения F1'!$D$20,"НИЖЕ РЕЗЕРВА","РЕЗЕРВ ЕСТЬ") -> РЕЗЕРВ ЕСТЬ
A4: ='План месяцев F1'!A4 -> 3 | B4: ='План месяцев F1'!C4 -> 80 | C4: =B4*'Допущения F1'!$D$4 -> 28 | D4: =C4*'Допущения F1'!$D$5 -> 16.8 | E4: =D4*'Допущения F1'!$D$6 -> 5.04 | F4: ='План месяцев F1'!D4 -> 0 | G4: =H3*'Допущения F1'!$D$7 -> 0.186732 | H4: =H3-G4+E4+F4 -> 11.077668 | I4: =(H3+H4)/2 -> 8.651034 | J4: ='Допущения F1'!$D$8 -> 19900 | K4: =H4*J4 -> 220445.59 | L4: ='План месяцев F1'!E4*'Допущения F1'!$D$17 -> 0 | M4: ='План месяцев F1'!F4*'Допущения F1'!$D$16 -> 0 | N4: =I4*J4+L4+M4 -> 172155.58 | O4: =(I4*'Допущения F1'!$D$9+'План месяцев F1'!F4)*('Допущения F1'!$D$10+'План месяцев F1'!G4*'Допущения F1'!$D$11*'Допущения F1'!$D$12)+F4*J4*'Допущения F1'!$D$15+L4*'План месяцев F1'!G4 -> 64882.755 | P4: =N4-O4 -> 107272.82 | Q4: ='План месяцев F1'!H4+'Допущения F1'!$D$18 -> 30000 | R4: =U4*'Допущения F1'!$D$14 -> 9818.4418 | S4: =MAX(0,'Допущения F1'!$D$19-'Допущения F1'!$D$18) -> 60000 | T4: =P4-Q4-R4-S4 -> 7454.3798 | U4: =N4*(1-'Допущения F1'!$D$13)+(N3)*'Допущения F1'!$D$13 -> 163640.7 | V4: =O4+Q4+R4 -> 104701.2 | W4: ='План месяцев F1'!I4 -> 0 | X4: =X3+U4-V4+W4 -> 172875.3 | Y4: =IF(X4<Q4*'Допущения F1'!$D$20,"НИЖЕ РЕЗЕРВА","РЕЗЕРВ ЕСТЬ") -> РЕЗЕРВ ЕСТЬ
A5: ='План месяцев F1'!A5 -> 4 | B5: ='План месяцев F1'!C5 -> 100 | C5: =B5*'Допущения F1'!$D$4 -> 35 | D5: =C5*'Допущения F1'!$D$5 -> 21 | E5: =D5*'Допущения F1'!$D$6 -> 6.3 | F5: ='План месяцев F1'!D5 -> 0 | G5: =H4*'Допущения F1'!$D$7 -> 0.33233004 | H5: =H4-G5+E5+F5 -> 17.045338 | I5: =(H4+H5)/2 -> 14.061503 | J5: ='Допущения F1'!$D$8 -> 19900 | K5: =H5*J5 -> 339202.23 | L5: ='План месяцев F1'!E5*'Допущения F1'!$D$17 -> 0 | M5: ='План месяцев F1'!F5*'Допущения F1'!$D$16 -> 0 | N5: =I5*J5+L5+M5 -> 279823.91 | O5: =(I5*'Допущения F1'!$D$9+'План месяцев F1'!F5)*('Допущения F1'!$D$10+'План месяцев F1'!G5*'Допущения F1'!$D$11*'Допущения F1'!$D$12)+F5*J5*'Допущения F1'!$D$15+L5*'План месяцев F1'!G5 -> 105461.27 | P5: =N5-O5 -> 174362.64 | Q5: ='План месяцев F1'!H5+'Допущения F1'!$D$18 -> 40000 | R5: =U5*'Допущения F1'!$D$14 -> 16143.425 | S5: =MAX(0,'Допущения F1'!$D$19-'Допущения F1'!$D$18) -> 60000 | T5: =P5-Q5-R5-S5 -> 58219.212 | U5: =N5*(1-'Допущения F1'!$D$13)+(N4)*'Допущения F1'!$D$13 -> 269057.08 | V5: =O5+Q5+R5 -> 161604.7 | W5: ='План месяцев F1'!I5 -> 0 | X5: =X4+U5-V5+W5 -> 280327.68 | Y5: =IF(X5<Q5*'Допущения F1'!$D$20,"НИЖЕ РЕЗЕРВА","РЕЗЕРВ ЕСТЬ") -> РЕЗЕРВ ЕСТЬ
A6: ='План месяцев F1'!A6 -> 5 | B6: ='План месяцев F1'!C6 -> 120 | C6: =B6*'Допущения F1'!$D$4 -> 42 | D6: =C6*'Допущения F1'!$D$5 -> 25.2 | E6: =D6*'Допущения F1'!$D$6 -> 7.56 | F6: ='План месяцев F1'!D6 -> 0 | G6: =H5*'Допущения F1'!$D$7 -> 0.51136014 | H6: =H5-G6+E6+F6 -> 24.093978 | I6: =(H5+H6)/2 -> 20.569658 | J6: ='Допущения F1'!$D$8 -> 19900 | K6: =H6*J6 -> 479470.16 | L6: ='План месяцев F1'!E6*'Допущения F1'!$D$17 -> 0 | M6: ='План месяцев F1'!F6*'Допущения F1'!$D$16 -> 0 | N6: =I6*J6+L6+M6 -> 409336.19 | O6: =(I6*'Допущения F1'!$D$9+'План месяцев F1'!F6)*('Допущения F1'!$D$10+'План месяцев F1'!G6*'Допущения F1'!$D$11*'Допущения F1'!$D$12)+F6*J6*'Допущения F1'!$D$15+L6*'План месяцев F1'!G6 -> 154272.43 | P6: =N6-O6 -> 255063.76 | Q6: ='План месяцев F1'!H6+'Допущения F1'!$D$18 -> 40000 | R6: =U6*'Допущения F1'!$D$14 -> 23783.098 | S6: =MAX(0,'Допущения F1'!$D$19-'Допущения F1'!$D$18) -> 60000 | T6: =P6-Q6-R6-S6 -> 131280.66 | U6: =N6*(1-'Допущения F1'!$D$13)+(N5)*'Допущения F1'!$D$13 -> 396384.96 | V6: =O6+Q6+R6 -> 218055.53 | W6: ='План месяцев F1'!I6 -> 0 | X6: =X5+U6-V6+W6 -> 458657.11 | Y6: =IF(X6<Q6*'Допущения F1'!$D$20,"НИЖЕ РЕЗЕРВА","РЕЗЕРВ ЕСТЬ") -> РЕЗЕРВ ЕСТЬ
A7: ='План месяцев F1'!A7 -> 6 | B7: ='План месяцев F1'!C7 -> 140 | C7: =B7*'Допущения F1'!$D$4 -> 49 | D7: =C7*'Допущения F1'!$D$5 -> 29.4 | E7: =D7*'Допущения F1'!$D$6 -> 8.82 | F7: ='План месяцев F1'!D7 -> 0 | G7: =H6*'Допущения F1'!$D$7 -> 0.72281933 | H7: =H6-G7+E7+F7 -> 32.191158 | I7: =(H6+H7)/2 -> 28.142568 | J7: ='Допущения F1'!$D$8 -> 19900 | K7: =H7*J7 -> 640604.05 | L7: ='План месяцев F1'!E7*'Допущения F1'!$D$17 -> 0 | M7: ='План месяцев F1'!F7*'Допущения F1'!$D$16 -> 0 | N7: =I7*J7+L7+M7 -> 560037.11 | O7: =(I7*'Допущения F1'!$D$9+'План месяцев F1'!F7)*('Допущения F1'!$D$10+'План месяцев F1'!G7*'Допущения F1'!$D$11*'Допущения F1'!$D$12)+F7*J7*'Допущения F1'!$D$15+L7*'План месяцев F1'!G7 -> 211069.26 | P7: =N7-O7 -> 348967.85 | Q7: ='План месяцев F1'!H7+'Допущения F1'!$D$18 -> 40000 | R7: =U7*'Допущения F1'!$D$14 -> 32698.021 | S7: =MAX(0,'Допущения F1'!$D$19-'Допущения F1'!$D$18) -> 60000 | T7: =P7-Q7-R7-S7 -> 216269.82 | U7: =N7*(1-'Допущения F1'!$D$13)+(N6)*'Допущения F1'!$D$13 -> 544967.01 | V7: =O7+Q7+R7 -> 283767.28 | W7: ='План месяцев F1'!I7 -> 0 | X7: =X6+U7-V7+W7 -> 719856.84 | Y7: =IF(X7<Q7*'Допущения F1'!$D$20,"НИЖЕ РЕЗЕРВА","РЕЗЕРВ ЕСТЬ") -> РЕЗЕРВ ЕСТЬ
A8: ='План месяцев F1'!A8 -> 7 | B8: ='План месяцев F1'!C8 -> 160 | C8: =B8*'Допущения F1'!$D$4 -> 56 | D8: =C8*'Допущения F1'!$D$5 -> 33.6 | E8: =D8*'Допущения F1'!$D$6 -> 10.08 | F8: ='План месяцев F1'!D8 -> 0 | G8: =H7*'Допущения F1'!$D$7 -> 0.96573475 | H8: =H7-G8+E8+F8 -> 41.305424 | I8: =(H7+H8)/2 -> 36.748291 | J8: ='Допущения F1'!$D$8 -> 19900 | K8: =H8*J8 -> 821977.93 | L8: ='План месяцев F1'!E8*'Допущения F1'!$D$17 -> 0 | M8: ='План месяцев F1'!F8*'Допущения F1'!$D$16 -> 0 | N8: =I8*J8+L8+M8 -> 731290.99 | O8: =(I8*'Допущения F1'!$D$9+'План месяцев F1'!F8)*('Допущения F1'!$D$10+'План месяцев F1'!G8*'Допущения F1'!$D$11*'Допущения F1'!$D$12)+F8*J8*'Допущения F1'!$D$15+L8*'План месяцев F1'!G8 -> 275612.18 | P8: =N8-O8 -> 455678.81 | Q8: ='План месяцев F1'!H8+'Допущения F1'!$D$18 -> 50000 | R8: =U8*'Допущения F1'!$D$14 -> 42849.936 | S8: =MAX(0,'Допущения F1'!$D$19-'Допущения F1'!$D$18) -> 60000 | T8: =P8-Q8-R8-S8 -> 302828.87 | U8: =N8*(1-'Допущения F1'!$D$13)+(N7)*'Допущения F1'!$D$13 -> 714165.6 | V8: =O8+Q8+R8 -> 368462.12 | W8: ='План месяцев F1'!I8 -> 0 | X8: =X7+U8-V8+W8 -> 1065560.3 | Y8: =IF(X8<Q8*'Допущения F1'!$D$20,"НИЖЕ РЕЗЕРВА","РЕЗЕРВ ЕСТЬ") -> РЕЗЕРВ ЕСТЬ
A9: ='План месяцев F1'!A9 -> 8 | B9: ='План месяцев F1'!C9 -> 180 | C9: =B9*'Допущения F1'!$D$4 -> 63 | D9: =C9*'Допущения F1'!$D$5 -> 37.8 | E9: =D9*'Допущения F1'!$D$6 -> 11.34 | F9: ='План месяцев F1'!D9 -> 0 | G9: =H8*'Допущения F1'!$D$7 -> 1.2391627 | H9: =H8-G9+E9+F9 -> 51.406261 | I9: =(H8+H9)/2 -> 46.355842 | J9: ='Допущения F1'!$D$8 -> 19900 | K9: =H9*J9 -> 1022984.6 | L9: ='План месяцев F1'!E9*'Допущения F1'!$D$17 -> 0 | M9: ='План месяцев F1'!F9*'Допущения F1'!$D$16 -> 0 | N9: =I9*J9+L9+M9 -> 922481.26 | O9: =(I9*'Допущения F1'!$D$9+'План месяцев F1'!F9)*('Допущения F1'!$D$10+'План месяцев F1'!G9*'Допущения F1'!$D$11*'Допущения F1'!$D$12)+F9*J9*'Допущения F1'!$D$15+L9*'План месяцев F1'!G9 -> 347668.82 | P9: =N9-O9 -> 574812.45 | Q9: ='План месяцев F1'!H9+'Допущения F1'!$D$18 -> 50000 | R9: =U9*'Допущения F1'!$D$14 -> 54201.734 | S9: =MAX(0,'Допущения F1'!$D$19-'Допущения F1'!$D$18) -> 60000 | T9: =P9-Q9-R9-S9 -> 410610.71 | U9: =N9*(1-'Допущения F1'!$D$13)+(N8)*'Допущения F1'!$D$13 -> 903362.24 | V9: =O9+Q9+R9 -> 451870.55 | W9: ='План месяцев F1'!I9 -> 0 | X9: =X8+U9-V9+W9 -> 1517052 | Y9: =IF(X9<Q9*'Допущения F1'!$D$20,"НИЖЕ РЕЗЕРВА","РЕЗЕРВ ЕСТЬ") -> РЕЗЕРВ ЕСТЬ
A10: ='План месяцев F1'!A10 -> 9 | B10: ='План месяцев F1'!C10 -> 200 | C10: =B10*'Допущения F1'!$D$4 -> 70 | D10: =C10*'Допущения F1'!$D$5 -> 42 | E10: =D10*'Допущения F1'!$D$6 -> 12.6 | F10: ='План месяцев F1'!D10 -> 0 | G10: =H9*'Допущения F1'!$D$7 -> 1.5421878 | H10: =H9-G10+E10+F10 -> 62.464073 | I10: =(H9+H10)/2 -> 56.935167 | J10: ='Допущения F1'!$D$8 -> 19900 | K10: =H10*J10 -> 1243035.1 | L10: ='План месяцев F1'!E10*'Допущения F1'!$D$17 -> 0 | M10: ='План месяцев F1'!F10*'Допущения F1'!$D$16 -> 0 | N10: =I10*J10+L10+M10 -> 1133009.8 | O10: =(I10*'Допущения F1'!$D$9+'План месяцев F1'!F10)*('Допущения F1'!$D$10+'План месяцев F1'!G10*'Допущения F1'!$D$11*'Допущения F1'!$D$12)+F10*J10*'Допущения F1'!$D$15+L10*'План месяцев F1'!G10 -> 427013.75 | P10: =N10-O10 -> 705996.07 | Q10: ='План месяцев F1'!H10+'Допущения F1'!$D$18 -> 50000 | R10: =U10*'Допущения F1'!$D$14 -> 66717.418 | S10: =MAX(0,'Допущения F1'!$D$19-'Допущения F1'!$D$18) -> 60000 | T10: =P10-Q10-R10-S10 -> 529278.65 | U10: =N10*(1-'Допущения F1'!$D$13)+(N9)*'Допущения F1'!$D$13 -> 1111957 | V10: =O10+Q10+R10 -> 543731.17 | W10: ='План месяцев F1'!I10 -> 0 | X10: =X9+U10-V10+W10 -> 2085277.8 | Y10: =IF(X10<Q10*'Допущения F1'!$D$20,"НИЖЕ РЕЗЕРВА","РЕЗЕРВ ЕСТЬ") -> РЕЗЕРВ ЕСТЬ
A11: ='План месяцев F1'!A11 -> 10 | B11: ='План месяцев F1'!C11 -> 220 | C11: =B11*'Допущения F1'!$D$4 -> 77 | D11: =C11*'Допущения F1'!$D$5 -> 46.2 | E11: =D11*'Допущения F1'!$D$6 -> 13.86 | F11: ='План месяцев F1'!D11 -> 0 | G11: =H10*'Допущения F1'!$D$7 -> 1.8739222 | H11: =H10-G11+E11+F11 -> 74.450151 | I11: =(H10+H11)/2 -> 68.457112 | J11: ='Допущения F1'!$D$8 -> 19900 | K11: =H11*J11 -> 1481558 | L11: ='План месяцев F1'!E11*'Допущения F1'!$D$17 -> 0 | M11: ='План месяцев F1'!F11*'Допущения F1'!$D$16 -> 0 | N11: =I11*J11+L11+M11 -> 1362296.5 | O11: =(I11*'Допущения F1'!$D$9+'План месяцев F1'!F11)*('Допущения F1'!$D$10+'План месяцев F1'!G11*'Допущения F1'!$D$11*'Допущения F1'!$D$12)+F11*J11*'Допущения F1'!$D$15+L11*'План месяцев F1'!G11 -> 513428.34 | P11: =N11-O11 -> 848868.19 | Q11: ='План месяцев F1'!H11+'Допущения F1'!$D$18 -> 60000 | R11: =U11*'Допущения F1'!$D$14 -> 80362.072 | S11: =MAX(0,'Допущения F1'!$D$19-'Допущения F1'!$D$18) -> 60000 | T11: =P11-Q11-R11-S11 -> 648506.12 | U11: =N11*(1-'Допущения F1'!$D$13)+(N10)*'Допущения F1'!$D$13 -> 1339367.9 | V11: =O11+Q11+R11 -> 653790.41 | W11: ='План месяцев F1'!I11 -> 0 | X11: =X10+U11-V11+W11 -> 2770855.3 | Y11: =IF(X11<Q11*'Допущения F1'!$D$20,"НИЖЕ РЕЗЕРВА","РЕЗЕРВ ЕСТЬ") -> РЕЗЕРВ ЕСТЬ
A12: ='План месяцев F1'!A12 -> 11 | B12: ='План месяцев F1'!C12 -> 240 | C12: =B12*'Допущения F1'!$D$4 -> 84 | D12: =C12*'Допущения F1'!$D$5 -> 50.4 | E12: =D12*'Допущения F1'!$D$6 -> 15.12 | F12: ='План месяцев F1'!D12 -> 0 | G12: =H11*'Допущения F1'!$D$7 -> 2.2335045 | H12: =H11-G12+E12+F12 -> 87.336646 | I12: =(H11+H12)/2 -> 80.893399 | J12: ='Допущения F1'!$D$8 -> 19900 | K12: =H12*J12 -> 1737999.3 | L12: ='План месяцев F1'!E12*'Допущения F1'!$D$17 -> 0 | M12: ='План месяцев F1'!F12*'Допущения F1'!$D$16 -> 0 | N12: =I12*J12+L12+M12 -> 1609778.6 | O12: =(I12*'Допущения F1'!$D$9+'План месяцев F1'!F12)*('Допущения F1'!$D$10+'План месяцев F1'!G12*'Допущения F1'!$D$11*'Допущения F1'!$D$12)+F12*J12*'Допущения F1'!$D$15+L12*'План месяцев F1'!G12 -> 606700.49 | P12: =N12-O12 -> 1003078.1 | Q12: ='План месяцев F1'!H12+'Допущения F1'!$D$18 -> 60000 | R12: =U12*'Допущения F1'!$D$14 -> 95101.825 | S12: =MAX(0,'Допущения F1'!$D$19-'Допущения F1'!$D$18) -> 60000 | T12: =P12-Q12-R12-S12 -> 787976.32 | U12: =N12*(1-'Допущения F1'!$D$13)+(N11)*'Допущения F1'!$D$13 -> 1585030.4 | V12: =O12+Q12+R12 -> 761802.32 | W12: ='План месяцев F1'!I12 -> 0 | X12: =X11+U12-V12+W12 -> 3594083.4 | Y12: =IF(X12<Q12*'Допущения F1'!$D$20,"НИЖЕ РЕЗЕРВА","РЕЗЕРВ ЕСТЬ") -> РЕЗЕРВ ЕСТЬ
A13: ='План месяцев F1'!A13 -> 12 | B13: ='План месяцев F1'!C13 -> 260 | C13: =B13*'Допущения F1'!$D$4 -> 91 | D13: =C13*'Допущения F1'!$D$5 -> 54.6 | E13: =D13*'Допущения F1'!$D$6 -> 16.38 | F13: ='План месяцев F1'!D13 -> 0 | G13: =H12*'Допущения F1'!$D$7 -> 2.6200994 | H13: =H12-G13+E13+F13 -> 101.09655 | I13: =(H12+H13)/2 -> 94.216597 | J13: ='Допущения F1'!$D$8 -> 19900 | K13: =H13*J13 -> 2011821.3 | L13: ='План месяцев F1'!E13*'Допущения F1'!$D$17 -> 0 | M13: ='План месяцев F1'!F13*'Допущения F1'!$D$16 -> 0 | N13: =I13*J13+L13+M13 -> 1874910.3 | O13: =(I13*'Допущения F1'!$D$9+'План месяцев F1'!F13)*('Допущения F1'!$D$10+'План месяцев F1'!G13*'Допущения F1'!$D$11*'Допущения F1'!$D$12)+F13*J13*'Допущения F1'!$D$15+L13*'План месяцев F1'!G13 -> 706624.48 | P13: =N13-O13 -> 1168285.8 | Q13: ='План месяцев F1'!H13+'Допущения F1'!$D$18 -> 60000 | R13: =U13*'Допущения F1'!$D$14 -> 110903.83 | S13: =MAX(0,'Допущения F1'!$D$19-'Допущения F1'!$D$18) -> 60000 | T13: =P13-Q13-R13-S13 -> 937381.97 | U13: =N13*(1-'Допущения F1'!$D$13)+(N12)*'Допущения F1'!$D$13 -> 1848397.1 | V13: =O13+Q13+R13 -> 877528.3 | W13: ='План месяцев F1'!I13 -> 0 | X13: =X12+U13-V13+W13 -> 4564952.2 | Y13: =IF(X13<Q13*'Допущения F1'!$D$20,"НИЖЕ РЕЗЕРВА","РЕЗЕРВ ЕСТЬ") -> РЕЗЕРВ ЕСТЬ

Sheet Проверки Checks
A1: Проверка | B1: Отклонение / факт | C1: Ожидание | D1: Статус | E1: Пояснение
A2: Разложение каталога | B2: =COUNTA('Каталог F1'!A2:A58) -> 57 | C2: 57 | D2: =IF(ABS(B2-C2)<0.01,"OK","ОШИБКА") -> OK | E2: Без parent/child-дедупликации; записи, не сервисы
A3: Уникальные ID сигналов | B3: =COUNTA('Сигналы F1'!A2:A126) -> 125 | C3: 125 | D3: =IF(ABS(B3-C3)<0.01,"OK","ОШИБКА") -> OK | E3: Пересказы сохранены полностью
A4: Слабый F1: мост кассы м1 | B4: =ROUND('Слабый F1'!X2-('Допущения F1'!B2-'Допущения F1'!B3+'Слабый F1'!U2-'Слабый F1'!V2+'Слабый F1'!W2),2) -> 0 | C4: 0 | D4: =IF(ABS(B4-C4)<0.01,"OK","ОШИБКА") -> OK | E4: Открытие + поступления - расходы + подтверждённые деньги
A5: Слабый F1: сумма нач. выручки | B5: =ROUND(SUM('Слабый F1'!N2:N13)-SUMPRODUCT('Слабый F1'!I2:I13,'Слабый F1'!J2:J13)-SUM('Слабый F1'!L2:L13)-SUM('Слабый F1'!M2:M13),2) -> 0 | C5: 0 | D5: =IF(ABS(B5-C5)<0.01,"OK","ОШИБКА") -> OK | E5: Подписка по средним клиентам + отдельные платежи
A6: Слабый F1: финальная дебиторка | B6: =ROUND(SUM('Слабый F1'!N2:N13)-SUM('Слабый F1'!U2:U13)-'Слабый F1'!N13*'Допущения F1'!B13,2) -> 0 | C6: 0 | D6: =IF(ABS(B6-C6)<0.01,"OK","ОШИБКА") -> OK | E6: Начислено - получено = задержанная выручка м12
A7: Рабочий F1: мост кассы м1 | B7: =ROUND('Рабочий F1'!X2-('Допущения F1'!C2-'Допущения F1'!C3+'Рабочий F1'!U2-'Рабочий F1'!V2+'Рабочий F1'!W2),2) -> 0 | C7: 0 | D7: =IF(ABS(B7-C7)<0.01,"OK","ОШИБКА") -> OK | E7: Открытие + поступления - расходы + подтверждённые деньги
A8: Рабочий F1: сумма нач. выручки | B8: =ROUND(SUM('Рабочий F1'!N2:N13)-SUMPRODUCT('Рабочий F1'!I2:I13,'Рабочий F1'!J2:J13)-SUM('Рабочий F1'!L2:L13)-SUM('Рабочий F1'!M2:M13),2) -> 0 | C8: 0 | D8: =IF(ABS(B8-C8)<0.01,"OK","ОШИБКА") -> OK | E8: Подписка по средним клиентам + отдельные платежи
A9: Рабочий F1: финальная дебиторка | B9: =ROUND(SUM('Рабочий F1'!N2:N13)-SUM('Рабочий F1'!U2:U13)-'Рабочий F1'!N13*'Допущения F1'!C13,2) -> 0 | C9: 0 | D9: =IF(ABS(B9-C9)<0.01,"OK","ОШИБКА") -> OK | E9: Начислено - получено = задержанная выручка м12
A10: Сильный F1: мост кассы м1 | B10: =ROUND('Сильный F1'!X2-('Допущения F1'!D2-'Допущения F1'!D3+'Сильный F1'!U2-'Сильный F1'!V2+'Сильный F1'!W2),2) -> 0 | C10: 0 | D10: =IF(ABS(B10-C10)<0.01,"OK","ОШИБКА") -> OK | E10: Открытие + поступления - расходы + подтверждённые деньги
A11: Сильный F1: сумма нач. выручки | B11: =ROUND(SUM('Сильный F1'!N2:N13)-SUMPRODUCT('Сильный F1'!I2:I13,'Сильный F1'!J2:J13)-SUM('Сильный F1'!L2:L13)-SUM('Сильный F1'!M2:M13),2) -> 0 | C11: 0 | D11: =IF(ABS(B11-C11)<0.01,"OK","ОШИБКА") -> OK | E11: Подписка по средним клиентам + отдельные платежи
A12: Сильный F1: финальная дебиторка | B12: =ROUND(SUM('Сильный F1'!N2:N13)-SUM('Сильный F1'!U2:U13)-'Сильный F1'!N13*'Допущения F1'!D13,2) -> 0 | C12: 0 | D12: =IF(ABS(B12-C12)<0.01,"OK","ОШИБКА") -> OK | E12: Начислено - получено = задержанная выручка м12

Sheet Каталог F1
A1: ID архива | B1: Итоговая функция / запись | C1: Класс записи | D1: Решение F1 | E1: Описание из исследования — НЕ обещание | F1: Блокер из архива | G1: Условие перехода | H1: Требует проверки | I1: Источник
A2: S-01 | B2: ИИ-конвейер оплаты субподрядчика | C2: Клиентская возможность | D2: MVP | E2: КС-2/КС-3 под форму заказчика → напоминание → претензия с расчётом процентов → уведомление о приостановке (ст. 719/328) → карта сделки → иск-готовность | F2: нет (доставка e-mail/Почта по API) | G2: Один полный маршрут: корректные входы, юрист, контроль отправки, доказательства, журнал, экспорт, тесты | H2: Не подтверждён архивом; старые месяцы готовности и баллы не доказательство | I2: Capexly_BusinessPlan_v2.xlsx / Каталог_57
A3: S-02 | B3: Классификатор препятствий и уведомления ст. 716/718/719/406 | C3: Клиентская возможность | D3: MVP | E3: Определяет основание (материалы, неоплата, непередача площадки/ПД) и формирует уведомление + требование об изменении сроков | F3: нет | G3: Один полный маршрут: корректные входы, юрист, контроль отправки, доказательства, журнал, экспорт, тесты | H3: Не подтверждён архивом; старые месяцы готовности и баллы не доказательство | I3: Capexly_BusinessPlan_v2.xlsx / Каталог_57
A4: S-03 | B4: Претензия об оплате с расчётом (ст. 395/330) | C4: Клиентская возможность | D4: MVP | E4: Расчёт процентов/неустойки по договору, доставка на все адреса, таймер досудебного срока (ч. 5 ст. 4 АПК) | F4: нет | G4: Один полный маршрут: корректные входы, юрист, контроль отправки, доказательства, журнал, экспорт, тесты | H4: Не подтверждён архивом; старые месяцы готовности и баллы не доказательство | I4: Capexly_BusinessPlan_v2.xlsx / Каталог_57
A5: S-04 | B5: Односторонний акт и вызов на приёмку (ст. 753) | C5: Клиентская возможность | D5: MVP | E5: Уведомление о готовности, вызов на приёмку, односторонний акт при уклонении, таймер мотивированного отказа | F5: нет | G5: Один полный маршрут: корректные входы, юрист, контроль отправки, доказательства, журнал, экспорт, тесты | H5: Не подтверждён архивом; старые месяцы готовности и баллы не доказательство | I5: Capexly_BusinessPlan_v2.xlsx / Каталог_57
A6: S-05 | B6: Проект мотивированного отказа; без автоматической остановки оплаты | C6: Клиентская возможность | D6: После пилотов | E6: Юридически значимый отказ от приёмки с перечнем недостатков и доставкой; блокировка оплаты до передачи ИД | F6: нет | G6: Платный спрос, тест-сет на реальных данных, отдельная приёмка | H6: Не подтверждён архивом; старые месяцы готовности и баллы не доказательство | I6: Capexly_BusinessPlan_v2.xlsx / Каталог_57
A7: S-06 | B7: ИИ-ворота оплаты генподрядчика (сверка КС-2 субподрядчика) | C7: Клиентская возможность | D7: После пилотов | E7: Сверка акта субподрядчика с ведомостью, сметой, накопительной и РД; лист расхождений → допуск к оплате или отказ | F7: качество семантической сверки — библиотека соответствий + ML (не вайбкодинг) | G7: Платный спрос, тест-сет на реальных данных, отдельная приёмка | H7: Не подтверждён архивом; старые месяцы готовности и баллы не доказательство | I7: Capexly_BusinessPlan_v2.xlsx / Каталог_57
A8: S-07 | B8: Калькулятор применимых сроков качества с проверкой юриста | C8: Клиентская возможность | D8: MVP | E8: Сроки обнаружения/устранения недостатков, гарантия, давность (ст. 724, 725, 756) | F8: нет | G8: Один полный маршрут: корректные входы, юрист, контроль отправки, доказательства, журнал, экспорт, тесты | H8: Не подтверждён архивом; старые месяцы готовности и баллы не доказательство | I8: Capexly_BusinessPlan_v2.xlsx / Каталог_57
A9: S-08 | B9: Таймер гарантийного удержания | C9: Клиентская возможность | D9: MVP | E9: Условия ГУ из договора → календарь возврата → претензия с процентами; контроль зачётов | F9: нет | G9: Один полный маршрут: корректные входы, юрист, контроль отправки, доказательства, журнал, экспорт, тесты | H9: Не подтверждён архивом; старые месяцы готовности и баллы не доказательство | I9: Capexly_BusinessPlan_v2.xlsx / Каталог_57
A10: S-09 | B10: ЕИС-акт пречек (44-ФЗ) | C10: Клиентская возможность | D10: GTM — не продукт | E10: Структурированный акт ЕИС ↔ смета контракта ↔ КС-2 ↔ график; валидатор ошибок, ведущих к отказу | F10: спецификация акта ЕИС открыта; подача — через кабинет клиента | G10: Коммерческий процесс; готовность измеряется отдельно | H10: Не подтверждён архивом; старые месяцы готовности и баллы не доказательство | I10: Capexly_BusinessPlan_v2.xlsx / Каталог_57
A11: S-10 | B11: ИИ-регресс к субподрядчику по гарантийному дефекту | C11: Клиентская возможность | D11: GTM — не продукт | E11: Обращение дольщика/УК → классификация по ГОСТ Р 72509 → виновный субподрядчик по АОСР → претензия и удержание из ГУ → таймер 60 дней | F11: для автоматизации — API helpdesk застройщика (Базис/Техзор, по согласованию) | G11: Коммерческий процесс; готовность измеряется отдельно | H11: Не подтверждён архивом; старые месяцы готовности и баллы не доказательство | I11: Capexly_BusinessPlan_v2.xlsx / Каталог_57
A12: S-11 | B12: Ответ на предписание/акт проверки ГСН, ходатайство о продлении | C12: Клиентская возможность | D12: Эксперимент | E12: Возражения, извещение об исполнении, ходатайство о продлении срока с валидатором процедуры | F12: нет | G12: Интервью и ручной оплаченный кейс до разработки | H12: Не подтверждён архивом; старые месяцы готовности и баллы не доказательство | I12: Capexly_BusinessPlan_v2.xlsx / Каталог_57
... A58: S-57 | B58: White-label для аутсорсеров ИД/ОТ/стройконтроля/КС | C58: Коммерческий процесс | D58: GTM — не продукт | E58: Движок валидаторов и доставки под брендом аутсорсера; оплата за объект | F58: партнёрский договор | G58: Коммерческий процесс; готовность измеряется отдельно | H58: Не подтверждён архивом; старые месяцы готовности и баллы не доказательство | I58: Capexly_BusinessPlan_v2.xlsx / Каталог_57

Sheet Сигналы F1
A1: ID | B1: Категория (внешн.) | C1: Сигнал (кратко) | D1: Флаг | E1: Сила | F1: Модуль Capexly | G1: Отношение | H1: Комментарий | I1: Статус F1
A2: S01 | B2: 1 Вакансии | C2: Массовые вакансии «инженер ПТО на исполнительную документацию» 100–250 тыс. руб. Функции: сверка КС-2/КС-3 с договорной ведомостью, АОСР, журналы, контроль работ по… | D2: [Ф] | E2: сильный | F2: M2, M5, P4 | G2: Подтверждает | H2: Ручная сверка КС-2 с договорной ведомостью — функция, за которую нанимают ПТО; это ядро платёжного конвейера и «ворот оплаты» | I2: Пересказ из Iter6; [Ф] не перепроверен
A3: S02 | B3: 1 Вакансии | C3: Инженер ПТО/сметчик — №1 по востребованности среди ИТР; 5,6% всех вакансий отрасли, hh.индекс 2,4; медиана предложений 120,2 тыс. (+21% г/г) при общем падении вакансий… | D3: [Ф] | E3: сильный | F3: M5, M1 | G3: Подтверждает | H3: ПТО/сметчик — самая дефицитная ИТР-роль; тезис «ИИ-бэк-офис вместо найма» подтверждён | I3: Пересказ из Iter6; [Ф] не перепроверен
A4: S03 | B4: 1 Вакансии | C4: Вакансия «специалист ОКС: контроль гарантийного сопровождения объектов в гарантийный срок, рассмотрение обращений граждан» — отдельная штатная функция у застройщиков | D4: [Ф] | E4: средний | F4: M8, M2 | G4: Дополняет | H4: Гарантийный отдел застройщика как отдельная роль → сегмент для M8 и «регресса к субподрядчику» | I4: Пересказ из Iter6; [Ф] не перепроверен
A5: S04 | B5: 1 Вакансии | C5: Вакансия «главный специалист: проверка актов НЗП на предмет превышений над договорной ведомостью и РД» — ручная сверка объёмов | D5: [Ф] | E5: средний | F5: M2 (ворота оплаты) | G5: Новое | H5: «Проверка актов НЗП на превышение над ведомостью/РД» — прямой запрос на сверку принимающей стороной (Sminex: 1 600 ч/цикл) | I5: Пересказ из Iter6; [Ф] не перепроверен
A6: S05 | B6: 1 Вакансии | C6: Рынок труда охлаждается (вакансии −12…−16%, резюме +11%), но зарплаты ПТО/прорабов растут на 17–21% — дефицит именно «документных» и линейных ИТР сохраняется | D6: [Ф]+[И] | E6: сильный | F6: все | G6: Подтверждает | H6: Зарплаты «документных» ИТР растут при охлаждении рынка — экономия часов монетизируема | I6: Пересказ из Iter6; [Ф] не перепроверен
A7: S06 | B7: 1 Вакансии / 7 Рынок | C7: Авито: подработка для инженеров-сметчиков +26%, отклики +86% (янв–май 2026); спрос на авторский надзор +51%, консультации для строителей +45%, строительную экспертизу… | D7: [Ф] | E7: сильный | F7: M4, M13 | G7: Дополняет | H7: Разовый спрос на экспертизу/авторский надзор/консультации +45–71% → поддерживает pay-per-doc | I7: Пересказ из Iter6; [Ф] не перепроверен
A8: S07 | B8: 1 Вакансии / 8 Финансы | C8: Оценки дефицита кадров противоречат друг другу: 160 тыс. (ВНИИ труда), 750 тыс. (НОСТРОЙ), ~1 млн (Минстрой); иностранных работников −35% за 2 года; 85% компаний —… | D8: [Ф] (противоречие зафиксировано) | E8: средний | F8: — | G8: Вне фокуса | H8: Противоречивые оценки дефицита кадров; использовать только с оговоркой | I8: Пересказ из Iter6; [Ф] не перепроверен
A9: S08 | B9: 1 Вакансии | C9: Зарплаты рабочих в июле 2026 +2,9% г/г против +13,9% годом ранее — рост остановился на фоне падения объёмов | D9: [Ф] | E9: слабый | F9: — | G9: Вне фокуса | H9: Зарплаты рабочих — вне фокуса | I9: Пересказ из Iter6; [Ф] не перепроверен
A10: S09 | B10: 2 Госзакупки | C10: Регионы закупают доработку/развитие ГИСОГД: Брянская 6,9 млн, Рязанская 20,9 млн (интеграция с ЕИСЖС и «Стройкомплекс»), Калининградская 14,2 млн на 2026 | D10: [Ф] | E10: средний | F10: P3 | G10: Вне фокуса | H10: Закупки ГИСОГД — покупатель государство (совпадает с их B7 и нашим отказом) | I10: Пересказ из Iter6; [Ф] не перепроверен
A11: S10 | B11: 2 Госзакупки | C11: Стройконтроль закупается как отдельная услуга: НМЦК 39,9 млн при реконструкции на 1,84 млрд (~2,2%); зафиксирован конфликт интересов — функции стройконтроля заказчика… | D11: [Ф] | E11: средний | F11: M10, M11 | G11: Дополняет | H11: Стройконтроль как услуга ~2,2% стоимости → аутсорсеры стройконтроля как партнёры/реселлеры | I11: Пересказ из Iter6; [Ф] не перепроверен
A12: S11 | B12: 2 Госзакупки / 3 Регуляторика | C12: Подрядчик на госзаказе платит за ВИС для передачи данных в ИСУП: тариф Exon привязан к сметной стоимости объекта — от 2 тыс. руб./мес (<5 млн) до 230 тыс. руб./мес (>4… | D12: [Ф] | E12: средний | F12: P3, M11 | G12: Корректирует | H12: Тариф ВИС по сметной стоимости (2–230 тыс. ₽/мес за объект) — ценовой якорь; наш ИСУП-коннектор только через партнёра-ВИС | I12: Пересказ из Iter6; [Ф] не перепроверен
... A81: S80 | B81: ОЧЕВИДНЫЙ (продажи) | C81: «Чат-бот/речевая аналитика застройщика»: продажи — уже один из самых цифровизированных этапов (44%); ДОМ.РФ приводит +13% конверсии от речевой аналитики | D81: [Ф] | E81: средний | F81: — | G81: Вне фокуса | H81: Чат-боты продаж — исключено | I81: Пересказ из Iter6; [Ф] не перепроверен
A82: S81 | B82: итерация 2 (проверка гипотез) | C82: hh.ru, активные вакансии по РФ, название+описание, снимок 14.10.2026: «инженер по гарантии» 178; «гарантийный отдел» 86 (совпало с итерацией 1 — метод воспроизводим);… | D82: [ФАКТ] одна платформа, один день | F82: M8 | G82: Дополняет | H82: hh: «инженер по гарантии» 178 — сегмент мал, но оформлен | I82: Пересказ из Iter6; [Ф] не перепроверен
A83: S82 | B83: итерация 2 (проверка гипотез) | C83: 2024: арбитражные суды рассмотрели 100 424 спора по договорам подряда, ~70% удовлетворены, взыскано >424 млрд руб., средний иск по строительному подряду ~9,4 млн руб.… | D83: [ФАКТ] вторичный | F83: M2 | G83: Подтверждает | H83: 100 424 спора по подряду в 2024, >424 млрд ₽, средний иск 9,4 млн ₽ — масштаб боли M2 | I83: Пересказ из Iter6; [Ф] не перепроверен
A84: S83 | B84: итерация 2 (проверка гипотез) | C84: В 2025 недочёты выявлены в 93% введённых МКД (центр «Аналитика. Бизнес. Право»); лимит компенсации 3% цены ДДУ не покрывает ремонт; принят ГОСТ Р 72509-2026 «Отделочные… | D84: [ФАКТ]+[МНЕНИЕ] | F84: M8 | G84: Подтверждает | H84: 93% МКД с дефектами; ГОСТ Р 72509 — наш M8 | I84: Пересказ из Iter6; [Ф] не перепроверен
A85: S84 | B85: итерация 2 (проверка гипотез) | C85: Мораторий на неустойки отменён с 01.01.2026; в 2024 — 78,2 тыс. исков дольщиков на ~50 млрд (+86%); в 2025 новых дел −45%; прогноз на 2026 — 80–100 тыс. исков, ~200… | D85: [ФАКТ]+[ОЦЕНКА] спикеров | F85: M8 | G85: Подтверждает | H85: 80–100 тыс. исков дольщиков в 2026 — давление на застройщиков → регресс к субподрядчикам | I85: Пересказ из Iter6; [Ф] не перепроверен
A86: S85 | B86: итерация 2 (проверка гипотез) | C86: Москвичи в 2025 взыскали с застройщиков >1 млрд руб. за дефекты отделки (экспертизы Мосгосстройнадзора); «значительное число споров регулируется без суда» | D86: [ФАКТ] вторичный | F86: M8 | G86: Подтверждает | H86: Москва >1 млрд ₽ взыскано за дефекты отделки | I86: Пересказ из Iter6; [Ф] не перепроверен
A87: S86 | B87: итерация 2 (проверка гипотез) | C87: Контур.Приёмка недвижимости: внутренняя приёмка 250 ₽/объект, клиентская 500 ₽/объект; заказ-наряды субподрядчикам, акты по шаблону, API к 1С/MacroCRM; гарантийного… | D87: [ФАКТ] | F87: M8 | G87: Корректирует | H87: Контур.Приёмка 250/500 ₽/объект — приёмку не строим; M8 = пред-приёмка + юридический регресс | I87: Пересказ из Iter6; [Ф] не перепроверен
A88: S87 | B88: итерация 2 (проверка гипотез) | C88: Цены аутсорса казначейского сопровождения: ведение 49–89 тыс. ₽/мес (kazna-gov), 105 тыс. ₽/мес фикс (kaznaexpert); «спасение контракта» от 35 тыс.; восстановление… | D88: [ФАКТ] прайсы консультантов | F88: M15 (кандидат) | G88: Новое | H88: Аутсорс казначейского сопровождения 49–105 тыс. ₽/мес — плательщик есть | I88: Пересказ из Iter6; [Ф] не перепроверен
A89: S88 | B89: итерация 2 (проверка гипотез) | C89: Приказ Минфина № 12н (ноябрь 2025): раздельный учёт стал самостоятельным приоритетным объектом контроля, на его основе формируется риск-профиль проекта; «казначейство… | D89: [МНЕНИЕ] | F89: M15 (кандидат) | G89: Новое | H89: Приказ Минфина 12н: раздельный учёт — риск-профиль → пречек платёжного пакета | I89: Пересказ из Iter6; [Ф] не перепроверен
A90: S89 | B90: итерация 2 (проверка гипотез) | C90: ПТО-ИИ (pto-ai.com): AI-проверка пакета ИД по 344/пр, СП 48, СП 70 — полнота/содержание/оформление, отчёт за 15 мин, от 49 900 ₽/мес, первые 100 страниц бесплатно;… | D90: [ФАКТ] цена; [МНЕНИЕ] вендора — метрики | F90: M5 | G90: Корректирует | H90: ПТО-ИИ 49 900 ₽/мес, безлимит объектов — ИИ-проверка ИД занята; M5 только pay-per-doc/«наследие» | I90: Пересказ из Iter6; [Ф] не перепроверен
A91: S90 | B91: итерация 2 (проверка гипотез) | C91: HARDROLLER: ИД-сервис 3 000 ₽/мес за пользователя (30 000 ₽/год), автоматические проверки несоответствия дат и отсутствия документов; отзыв «ИД по 10 объектам ведут 2… | D91: [ФАКТ] цена; [МНЕНИЕ] отзыв | F91: M5 | G91: Подтверждает | H91: HARDROLLER 3 000 ₽/польз. — уже в карте конкурентов iter 4 | I91: Пересказ из Iter6; [Ф] не перепроверен
A92: S91 | B92: итерация 2 (проверка гипотез) | C92: AIARM (aiarm.ru): универсальный ИИ-анализ документов, отраслевой сценарий «проверка КС-2/КС-3 — сверка с договором, сметой и предыдущими актами», генерация претензий,… | D92: [ФАКТ] | F92: M2 | G92: Корректирует | H92: AIARM: сверка КС-2/КС-3 + генерация претензий + калькулятор неустойки — жёлтая зона для M2; отличие — доставка/таймеры/доказательства/формы | I92: Пересказ из Iter6; [Ф] не перепроверен
A93: S92 | B93: итерация 2 (проверка гипотез) | C93: «Тенденция последних лет — системы автоматического распознавания ИД: программа сопоставляет данные из отсканированных АОСР с позициями в КС-2» | D93: [МНЕНИЕ] аутсорсера | F93: M5 | G93: Дополняет | H93: OCR АОСР ↔ позиции КС-2 — тренд, подтверждает P4 | I93: Пересказ из Iter6; [Ф] не перепроверен
... A126: S125 | B126: итерация 3 (опровержение) | C126: OCR/VLM на русских документах: chandra — CER 0,51%, Qwen2.5-VL-7B — 0,54–0,64% на печатных документах (Habr, команда ЧЗ, 27.04.2026); Qwen3 VL 30B A3B — лучший на… | D126: [ФАКТ] тесты | F126: P4 | G126: Корректирует | H126: OCR: печатные CER 0,5%; рукопись — только Qwen3-VL с оговорками → рукописный ОЖР остаётся ограничением | I126: Пересказ из Iter6; [Ф] не перепроверен

Sheet Тезисы F1
A1: ID | B1: Исходный тезис | C1: Оценка F1 | D1: Итоговая формулировка | E1: Опора | F1: Действие
A2: C01 | B2: 109/120 доказывает спрос | C2: Самооценка | D2: Скоринг — внутренний чек-лист; клиентских оплат он не доказывает. | E2: Все итерации, Дельта_120_v6 | F2: Снять с сайта и инвесторского резюме
A3: C02 | B3: 125 сигналов независимо подтверждают продукт | C3: Ограниченная проверяемость | D3: Сохранены 125 пересказов. Четыре исходных внешних файла отсутствуют; независимость и флаги [Ф] не проверены. | E3: Iter6, §1; CrossCheck / Сигналы→Capexly | F3: Запросить исходный внешний пакет
A4: C03 | B4: 57 готовых сервисов / 53% продукта на запуске | C4: Не подтверждено | D4: 57 записей: 41 клиентская, 11 платформенных, 5 GTM; есть родительские конвейеры и дочерние шаги. Фактической приёмки нет. | E4: BP_v2 / Каталог_57 | F4: Заменить на статус конкретного сценария
A5: C04 | B5: 424 млрд / 100424 = средний иск 9,4 млн | C5: Арифметическое расхождение | D5: Если основания сопоставимы: 424 млрд / 100424 = 4,22 млн; при >424 млрд — нижний ориентир, не точное среднее. Подряд не равен строительному подряду. | E5: BP_v2 §2; Iter4 §3 | F5: Убрать 9,4 млн и перепроверить статистическую форму
A6: C05 | B6: Все сценарии самофинансируются | C6: Противоречие | D6: Чувствительность v2 содержит -48 тыс. руб.; iter5 требует миллионы капитала. Зависит от состава команды, сроков платежей и скрытой работы основателя. | E6: BP_v2 / Чувствительность; Iter5 §7 | F6: Считать кассовый разрыв в формульной модели
A7: C06 | B7: Финансовая книга автоматически моделирует бизнес | C7: Техническое ограничение | D7: 23 листа v2, ноль формул. Старые цифры сохранены как снимок, а не работающий расчёт. | E7: Capexly_BusinessPlan_v2.xlsx | F7: Новая модель: входы → формулы → проверки
A8: C07 | B8: Любой корпоративный e-mail из реестра можно рекламно обрабатывать | C8: Риск / исправлено | D8: Открытый адрес и возможность отказа не заменяют предварительного согласия на рекламу. Персонализация сама по себе не даёт освобождения. | E8: BP_v2 §8; УФАС | F8: Входящие, рекомендации, партнёры и подтверждённое согласие
A9: C08 | B9: 243-ФЗ требует маркировать весь ИИ-контент с 01.03.2027 | C9: Частично / сужено | D9: Прочитанная правовая аналитика различает первоначальный проект и принятый рамочный закон; универсальная обязанность автора не подтверждена. | E9: ГАРАНТ 12.10.2026 | F9: Мониторить принятый текст и подзаконные акты
A10: C09 | B10: Уведомления СРО: три рабочих дня | C10: Частично подтверждено | D10: Разъяснение СРО подтверждает срок со следующего дня после события и приказ 655/пр. Формы, предмет договора и применимая СРО уточняются. | E10: Разъяснение ipsro.ru | F10: Юрист утверждает правило для каждого типа СРО
A11: C10 | B11: Штраф 100 тыс. за любой пропуск уведомления СРО | C11: Не подтверждено | D11: Сумму не использовать без конкретной статьи, состава, субъекта, редакции и применимости. Исключение и административный штраф — разные последствия. | E11: BP_v2 §2, §8 | F11: Удалить универсальную угрозу из оффера
A12: C11 | B12: Нет ИД → можно автоматически остановить оплату | C12: Опасное обобщение | D12: Связь ИД с оплатой зависит от договора, факта работ, существенности и судебного контекста. Отказ подтверждает человек. | E12: Iter6 факты vs S-05 | F12: Запрет автоматического стоп-платежа
... A23: C22 | B23: ARR включает разовые документы / net churn улучшается pay-per-doc | C23: Методологически неверно | D23: MRR и ARR только повторяемая контрактная выручка; разовые документы и outcome отдельно. NRR по одинаковым когортам подписки. | E23: Iter5 меморандум; BP_v2 финмодель | F23: Вынести разовые платежи из MRR/NRR

Sheet Источники Sources
A1: ID | B1: URL или домен | C1: Тип записи | D1: Где найдено / что проверено | E1: Статус
A2: R0001 | B2: http://region.council.gov.ru/activity/activities/round_tables/173840/ | C2: URL из архива | D2: Capexly_Research_Report_Iter2.md:445 | E2: Не перепроверено
A3: R0002 | B3: http://shmelbeton.ru/pravila-tsentralizovannoj-postavki-betona | C3: URL из архива | D3: Capexly_Research_Report_Iter2.md:400 | E3: Не перепроверено
A4: R0003 | B4: https://100tonn.com/vhodnoy-kontrol-materialov-i-oborudovaniya-chto-proveryayut-do-montazha/ | C4: URL из архива | D4: Capexly_Research_Report_Iter2.md:489 | E4: Не перепроверено
A5: R0004 | B5: https://101-app.com/blog/nds-5-procentov-2026-usn | C5: URL из архива | D5: Capexly_Research_Report_Iter2.md:384 | E5: Не перепроверено
A6: R0005 | B6: https://101-app.com/blog/nds-v-stroitelstve-2026-stavki-usn-dogovory-scheta-faktury | C6: URL из архива | D6: Capexly_Research_Report_Iter2.md:383 | E6: Не перепроверено
A7: R0006 | B7: https://1c-o.ru/blog/articles/1s-sverka-avtomaticheskaya-sverka-dokumentov-s-kontragentami-kak-podklyuchit-i-ispolzovat | C7: URL из архива | D7: Capexly_Research_Report_Iter2.md:490 | E7: Не перепроверено
A8: R0007 | B8: https://1seller.ru/ii-v-proverke-stroitelnoj-dokumentatsii-polnoe-rukovodstvo | C8: URL из архива | D8: Capexly_Research_Report_Iter2.md:453 | E8: Не перепроверено
A9: R0008 | B9: https://action-market.ru/blog/ohrana-truda/dezhurnye-siz-aktualnoe-rukovodstvo-dlya-rabotodatelej/ | C9: URL из архива | D9: Capexly_Research_Report_Iter2.md:375 | E9: Не перепроверено
A10: R0009 | B10: https://allweb.ru/novosti-it/samolet-zapystil-analog-microsoft-project-dlia-stroitelei/ | C10: URL из архива | D10: Capexly_Research_Report_Iter2.md:422 | E10: Не перепроверено
A11: R0010 | B11: https://banamind.ai/construction-progress-tracking/ai-construction-delay-analysis-software | C11: URL из архива | D11: Capexly_Research_Report_Iter2.md:474 | E11: Не перепроверено
A12: R0011 | B12: https://base.garant.ru/55724541/ | C12: URL из архива | D12: Capexly_Research_Report_Iter2.md:488 | E12: Не перепроверено
... A638: R0637 | B638: https://xasanskij-r25.gosweb.gosuslugi.ru/netcat_files/userfiles/2/Ekonomika/Msm_prezent.pdf | C638: Муниципальная публикация | D638: Маркировка: роль участника, товарные группы, дата 01.12.2026 | E638: Поисковое извлечение; не первичный нормативный акт

Sheet Не строить F1
A1: Зона / идея | B1: Причина из архива | C1: Сохранённое объяснение | D1: Статус
A2: ИИ-сметчик / подбор расценок ФСНБ, разбор ЛСР | B2: Красный океан: Smeta.AI, ПростоСмета, Сметрикс, ЯСМЕТЧИК, kt-team + Гранд-Смета/Smeta.ru; 850+ решений в каталогах; сметные вендоры добавляют ИИ сами (их B9) | C2: Красная зона + решение пользователя | D2: Решение из v2, не независимая оценка
A3: Конъюнктурный анализ цен / КАЦ по 421/пр (N6) | B3: Сметный контур исключён пользователем; «очевидная» ниша, контроль со стороны экспертизы | C3: Решение пользователя | D3: Решение из v2, не независимая оценка
A4: Строительная CRM / учёт | B4: Gectaro, Stworka, 101-app, Расклад, Битрикс24, MacroCRM; высокая цена ошибки, долгое внедрение | C4: Красная зона + решение пользователя | D4: Решение из v2, не независимая оценка
A5: BIM-коллизии / «ИИ-BIM» (B6) | B5: Tangl, SIGNAL, Pilot-BIM; покупатель — проектировщик/крупный застройщик | C5: Красная зона | D5: Решение из v2, не независимая оценка
A6: Фотопрогресс / CV на площадке | B6: Aiterus, SIGNAL, S.Monitoring, SOLUT, PlanRadar/Buildots; капиталоёмко, enterprise-цикл | C6: Красная зона, не ИИ-текст | D6: Решение из v2, не независимая оценка
A7: Стройконтроль (замечания/чек-листы) со стороны заказчика | B7: Техзор (от 35 тыс.), Адепт, Exon, Pragmacore, TERRA360; оставили только сторону подрядчика (ответ на предписание, досье) | C7: Красная зона — взяли обратную сторону | D7: Решение из v2, не независимая оценка
A8: Платформа ИД / ИИ-проверка ИД по 344/пр, СП 48/70 | B8: ПТО-ИИ от 49 900 ₽/мес, Exon 147–230 тыс./объект, ЦУС, АЛТИУС, BuildDocs; оставили «ИД-фабрику наследия» pay-per-doc и ЗОС-пречек согласованности | C8: Красная зона — взяли смежный угол | D8: Решение из v2, не независимая оценка
A9: Отдельный конвертер ИД в XML 344/пр (B10) | B9: XML1, DoXML, docxml.ru — коммодити; включён как функция ИД-фабрики | C9: Занято, функция | D9: Решение из v2, не независимая оценка
A10: Standalone сравнение версий чертежей (B11) | B10: Есть у Pilot-ICE и Exon; перенесено в ИЗМ-радар как «влияние изменений на срок и КС-2» | C10: Занято, функция | D10: Решение из v2, не независимая оценка
A11: Проверка договора подряда как отдельный продукт (N9) | B11: Контур.Фокус «ИИ-анализ договора» 6 900–9 900 ₽/год, ИскраБот бесплатно за 4 минуты; ниша «сломана» ценой; парсер договора оставлен как внутренний шаг | C11: Коммодити | D11: Решение из v2, не независимая оценка
A12: Helpdesk гарантийных обращений застройщика | B12: Базис «Гарантии», Техзор; оставили регресс к субподрядчику и ответ дольщику (документы, а не тикеты) | C12: Красная зона — взяли документную сторону | D12: Решение из v2, не независимая оценка
... A31: Аренда ИИ-«юриста-чат-бота» общего назначения | B31: Общие legaltech-боты не знают форм СРО/ГП, сроков договора, адресов доставки и не несут доказательств; суды не компенсируют переписку (А40-308575/2023) | C31: Не решает задачу «документ = деньги» | D31: Решение из v2, не независимая оценка

Sheet Финансирование F1
A1: Источник | B1: Принимать в кассу | C1: Следующее действие | D1: Ограничение
A2: Займ учредителя | B2: Только фактически внесённая сумма | C2: Подтвердить договор, остаток и расходы основателя | D2: В модели 150 тыс. — гипотеза из архива
A3: ФСИ / Сколково | B3: Ноль до договора и даты платежа | C3: Проверить действующий конкурс, допустимые статьи, права на результат | D3: Целевые средства не свободная операционная касса
A4: ФРИИ / seed | B4: Ноль до закрытия сделки | C4: Подготовить подтверждённые когорты, IP, бюджет и условия сделки | D4: Старые суммы и доли не term sheet
A5: Платный пилот | B5: После договора и согласно срокам оплаты | C5: Фиксировать scope, цену, приёмку, права и решение о продолжении | D5: Не дублировать с подпиской
A6: Данные, подпись, доставка | B6: Нужны действующие оферты и тест интеграций | C6: Стоимость включать отдельно или выставлять по факту | D6: В модели оплата доставки/подписи напрямую поставщику

Sheet Карта файлов F1
A1: Файл оригинального архива | B1: Тип | C1: Решение | D1: Куда / почему
A2: Capexly_BusinessPlan_v1.xlsx | B2: Версионный документ | C2: Сведено / заменено | D2: Старые файлы остаются в оригинальном архиве; итоговая редакция F1 одна
A3: Capexly_BusinessPlan_v2.xlsx | B3: Версионный документ | C3: Сведено / заменено | D3: Старые файлы остаются в оригинальном архиве; итоговая редакция F1 одна
A4: Capexly_Business_Plan_v1.docx | B4: Версионный документ | C4: Сведено / заменено | D4: Старые файлы остаются в оригинальном архиве; итоговая редакция F1 одна
A5: Capexly_Business_Plan_v1.md | B5: Версионный документ | C5: Сведено / заменено | D5: Старые файлы остаются в оригинальном архиве; итоговая редакция F1 одна
A6: Capexly_Business_Plan_v2.docx | B6: Версионный документ | C6: Сведено / заменено | D6: Старые файлы остаются в оригинальном архиве; итоговая редакция F1 одна
A7: Capexly_Business_Plan_v2.md | B7: Версионный документ | C7: Сведено / заменено | D7: Старые файлы остаются в оригинальном архиве; итоговая редакция F1 одна
A8: Capexly_CrossCheck_v6_iter6.xlsx | B8: Версионный документ | C8: Сведено / заменено | D8: Старые файлы остаются в оригинальном архиве; итоговая редакция F1 одна
A9: Capexly_Research_Report.docx | B9: Версионный документ | C9: Сведено / заменено | D9: Старые файлы остаются в оригинальном архиве; итоговая редакция F1 одна
A10: Capexly_Research_Report.md | B10: Версионный документ | C10: Сведено / заменено | D10: Старые файлы остаются в оригинальном архиве; итоговая редакция F1 одна
A11: Capexly_Research_Report_Iter2.docx | B11: Версионный документ | C11: Сведено / заменено | D11: Старые файлы остаются в оригинальном архиве; итоговая редакция F1 одна
A12: Capexly_Research_Report_Iter2.md | B12: Версионный документ | C12: Сведено / заменено | D12: Старые файлы остаются в оригинальном архиве; итоговая редакция F1 одна
... A145: notes_sources.md | B145: Исследовательские заметки | C145: Сведено | D145: Источники Sources, оговорки и след выводов сохранены в реестрах
